{"version": 0.6, "generator": "Overpass API 0.7.62.8 e802775f", "osm3s": {"timestamp_osm_base": "2026-01-16T06:12:00Z", "copyright": "The data included in this document is from www.openstreetmap.org. The data is made available under ODbL."}, "elements": [{"type": "node", "id": 35142941, "lat": 59.8668098, "lon": 17.6193513}, {"type": "node", "id": 35143913, "lat": 59.867003, "lon": 17.6153468}, {"type": "node", "id": 35143915, "lat": 59.8676666, "lon": 17.6016826}, {"type": "node", "id": 35144454, "lat": 59.867955, "lon": 17.5954843}, {"type": "node", "id": 35144455, "lat": 59.8680199, "lon": 17.5902843}, {"type": "node", "id": 35144456, "lat": 59.8680863, "lon": 17.5831602}, {"type": "node", "id": 35144835, "lat": 59.8682482, "lon": 17.580388}, {"type": "node", "id": 35144836, "lat": 59.8685929, "lon": 17.5761222}, {"type": "node", "id": 35144837, "lat": 59.8691487, "lon": 17.5690412}, {"type": "node", "id": 35146795, "lat": 59.8693943, "lon": 17.5658568}, {"type": "node", "id": 35146796, "lat": 59.8694187, "lon": 17.563857}, {"type": "node", "id": 35146797, "lat": 59.8693455, "lon": 17.5619787}, {"type": "node", "id": 35146798, "lat": 59.8692306, "lon": 17.5594195}, {"type": "node", "id": 35146799, "lat": 59.8692995, "lon": 17.5571364}, {"type": "node", "id": 35146800, "lat": 59.8693728, "lon": 17.5557717}, {"type": "node", "id": 35146801, "lat": 59.8697519, "lon": 17.5485791}, {"type": "node", "id": 35146802, "lat": 59.8701397, "lon": 17.5414981}, {"type": "node", "id": 35146803, "lat": 59.8705345, "lon": 17.5340124, "tags": {"railway": "signal", "railway:position:exact": "72.528", "railway:signal:direction": "forward", "railway:signal:distant": "SE:F\u00f6rsignal", "railway:signal:distant:form": "light", "railway:signal:position": "left", "ref": "U L4R"}}, {"type": "node", "id": 35146804, "lat": 59.8708936, "lon": 17.5273446}, {"type": "node", "id": 35146805, "lat": 59.8712684, "lon": 17.5202722}, {"type": "node", "id": 35146807, "lat": 59.871402, "lon": 17.5140065}, {"type": "node", "id": 35146809, "lat": 59.8714235, "lon": 17.5099725}, {"type": "node", "id": 35146810, "lat": 59.8713675, "lon": 17.5068053}, {"type": "node", "id": 35146811, "lat": 59.8711972, "lon": 17.4976799}, {"type": "node", "id": 248719851, "lat": 59.8652917, "lon": 17.6022681}, {"type": "node", "id": 248723201, "lat": 59.8673597, "lon": 17.6079768, "tags": {"crossing:barrier": "full", "crossing:light": "yes", "railway": "crossing"}}, {"type": "node", "id": 250034644, "lat": 59.8680678, "lon": 17.5843713}, {"type": "node", "id": 299145538, "lat": 59.8713583, "lon": 17.5168048, "tags": {"crossing:barrier": "full", "railway": "level_crossing"}}, {"type": "node", "id": 310341768, "lat": 59.8696528, "lon": 17.5504681, "tags": {"crossing:barrier": "full", "railway": "level_crossing"}}, {"type": "node", "id": 310342173, "lat": 59.8684401, "lon": 17.5779674, "tags": {"railway": "level_crossing"}}, {"type": "node", "id": 312576045, "lat": 59.8702939, "lon": 17.5386742, "tags": {"crossing:barrier": "no", "railway": "level_crossing"}}, {"type": "node", "id": 336459180, "lat": 59.8731666, "lon": 17.6082716}, {"type": "node", "id": 336459185, "lat": 59.8734348, "lon": 17.6080123}, {"type": "node", "id": 336459189, "lat": 59.8738551, "lon": 17.607578}, {"type": "node", "id": 336459194, "lat": 59.8742348, "lon": 17.6070469}, {"type": "node", "id": 336459197, "lat": 59.8747477, "lon": 17.606253}, {"type": "node", "id": 336459200, "lat": 59.8750923, "lon": 17.6057233}, {"type": "node", "id": 336459857, "lat": 59.8754883, "lon": 17.6051077}, {"type": "node", "id": 336459860, "lat": 59.8756347, "lon": 17.6047987}, {"type": "node", "id": 336459864, "lat": 59.8757338, "lon": 17.6044983}, {"type": "node", "id": 336459865, "lat": 59.8758243, "lon": 17.6040777}, {"type": "node", "id": 336459866, "lat": 59.875876, "lon": 17.6037516}, {"type": "node", "id": 873755498, "lat": 59.8670883, "lon": 17.6135674, "tags": {"name": "Uppsala norra", "railway": "technical_station", "railway:ref": "Una"}}, {"type": "node", "id": 2079822025, "lat": 59.8709078, "lon": 17.5270888, "tags": {"crossing:barrier": "full", "railway": "level_crossing"}}, {"type": "node", "id": 2162467917, "lat": 59.8668459, "lon": 17.617801}, {"type": "node", "id": 2162467918, "lat": 59.8668472, "lon": 17.618049}, {"type": "node", "id": 2162467919, "lat": 59.8668557, "lon": 17.6175709}, {"type": "node", "id": 2162467920, "lat": 59.8668523, "lon": 17.6184718, "tags": {"railway": "switch", "railway:local_operated": "no", "railway:switch": "default", "railway:switch:electric": "yes"}}, {"type": "node", "id": 2162467924, "lat": 59.8670552, "lon": 17.6142589}, {"type": "node", "id": 2162467934, "lat": 59.867249, "lon": 17.6095368}, {"type": "node", "id": 2162467941, "lat": 59.8673318, "lon": 17.6078824, "tags": {"crossing:barrier": "full", "crossing:light": "yes", "railway": "level_crossing"}}, {"type": "node", "id": 2162467943, "lat": 59.8673676, "lon": 17.6078439, "tags": {"crossing:barrier": "full", "crossing:light": "yes", "railway": "level_crossing"}}, {"type": "node", "id": 2162467944, "lat": 59.8673724, "lon": 17.6070514}, {"type": "node", "id": 2162467945, "lat": 59.8673939, "lon": 17.6067927}, {"type": "node", "id": 2162467946, "lat": 59.8674377, "lon": 17.6064007, "tags": {"railway": "switch", "railway:local_operated": "no", "railway:switch": "default", "railway:switch:electric": "yes"}}, {"type": "node", "id": 2162467952, "lat": 59.867898, "lon": 17.6107276}, {"type": "node", "id": 2162467953, "lat": 59.8714021, "lon": 17.5087646}, {"type": "node", "id": 2232302446, "lat": 59.8686273, "lon": 17.6100869}, {"type": "node", "id": 2232302449, "lat": 59.8691378, "lon": 17.6097749}, {"type": "node", "id": 2232302451, "lat": 59.8693577, "lon": 17.6097665}, {"type": "node", "id": 2232302453, "lat": 59.8701208, "lon": 17.6096944}, {"type": "node", "id": 2232302455, "lat": 59.8709287, "lon": 17.6095492}, {"type": "node", "id": 2232302457, "lat": 59.8714411, "lon": 17.6094112}, {"type": "node", "id": 2232302459, "lat": 59.8722963, "lon": 17.6090281}, {"type": "node", "id": 2232302462, "lat": 59.872985, "lon": 17.6085465}, {"type": "node", "id": 2431496539, "lat": 59.8730423, "lon": 17.6084927}, {"type": "node", "id": 2672743024, "lat": 59.8673437, "lon": 17.6076401, "tags": {"crossing:barrier": "full", "crossing:light": "yes", "railway": "crossing"}}, {"type": "node", "id": 2672743025, "lat": 59.8673795, "lon": 17.6075983, "tags": {"crossing:barrier": "full", "crossing:light": "yes", "railway": "crossing"}}, {"type": "node", "id": 2885581201, "lat": 59.874287, "lon": 17.5944542, "tags": {"bench": "yes", "highway": "bus_stop", "name": "Librob\u00e4ck", "network": "UL", "route_ref": "10;106;772;844", "shelter": "yes"}}, {"type": "node", "id": 4242668164, "lat": 59.8673254, "lon": 17.6080098, "tags": {"crossing:barrier": "full", "crossing:light": "yes", "railway": "crossing"}}, {"type": "node", "id": 4543588033, "lat": 59.8751634, "lon": 17.6056868}, {"type": "node", "id": 6848099889, "lat": 59.8783076, "lon": 17.6185298, "tags": {"bench": "yes", "bin": "no", "highway": "bus_stop", "name": "Fj\u00e4rdhundragatan", "network": "UL", "network:wikidata": "Q7899151", "route_ref": "8", "shelter": "no"}}, {"type": "node", "id": 6848099890, "lat": 59.8845032, "lon": 17.6146565, "tags": {"bench": "yes", "bin": "yes", "highway": "bus_stop", "name": "B\u00e4rbyparken", "network": "UL", "network:wikidata": "Q7899151", "route_ref": "8", "shelter": "yes"}}, {"type": "node", "id": 6848099891, "lat": 59.8855243, "lon": 17.6180711, "tags": {"bench": "yes", "bin": "yes", "highway": "bus_stop", "name": "B\u00e4rbygatan", "network": "UL", "network:wikidata": "Q7899151", "route_ref": "8", "shelter": "no"}}, {"type": "node", "id": 6848100094, "lat": 59.8825789, "lon": 17.6139339, "tags": {"bench": "no", "bin": "yes", "highway": "bus_stop", "name": "Flott\u00f6rgatan", "network": "UL", "network:wikidata": "Q7899151", "route_ref": "8", "shelter": "no"}}, {"type": "node", "id": 6848100095, "lat": 59.8845174, "lon": 17.6153076, "tags": {"bench": "no", "bin": "yes", "highway": "bus_stop", "name": "B\u00e4rbyparken", "network": "UL", "network:wikidata": "Q7899151", "route_ref": "8", "shelter": "no"}}, {"type": "node", "id": 6848100096, "lat": 59.887873, "lon": 17.6070826, "tags": {"bench": "yes", "bin": "yes", "highway": "bus_stop", "name": "Garnisonen", "network": "UL", "network:wikidata": "Q7899151", "route_ref": "8", "shelter": "yes"}}, {"type": "node", "id": 6848115002, "lat": 59.8775032, "lon": 17.5900934, "tags": {"bench": "yes", "highway": "bus_stop", "name": "H\u00e5lln\u00e4sgatan", "network": "UL", "route_ref": "10", "shelter": "yes"}}, {"type": "node", "id": 6848123497, "lat": 59.8718702, "lon": 17.5949264, "tags": {"bench": "no", "bin": "no", "highway": "bus_stop", "name": "Husbyborg", "network": "UL", "route_ref": "106", "shelter": "no"}}, {"type": "node", "id": 6848123498, "lat": 59.8719753, "lon": 17.5959858, "tags": {"bench": "no", "bin": "no", "highway": "bus_stop", "name": "Husbyborg", "network": "UL", "route_ref": "106", "shelter": "no"}}, {"type": "node", "id": 6848123551, "lat": 59.8714227, "lon": 17.6009562, "tags": {"bench": "no", "bin": "no", "highway": "bus_stop", "name": "Skebogatan", "network": "UL", "route_ref": "10", "shelter": "no", "tactile_paving": "yes"}}, {"type": "node", "id": 6848123552, "lat": 59.8738904, "lon": 17.5956067, "tags": {"bench": "yes", "highway": "bus_stop", "name": "Librob\u00e4ck", "network": "UL", "network:wikidata": "Q7899151", "route_ref": "10;106;772;844", "shelter": "yes"}}, {"type": "node", "id": 6848123553, "lat": 59.8776015, "lon": 17.5906016, "tags": {"bench": "no", "bin": "no", "highway": "bus_stop", "name": "H\u00e5lln\u00e4sgatan", "network": "UL", "route_ref": "10", "shelter": "no"}}, {"type": "node", "id": 6848125995, "lat": 59.8689392, "lon": 17.6059583, "tags": {"bench": "no", "bin": "no", "highway": "bus_stop", "lit": "yes", "local_ref": "A", "name": "Fyrisvallsgatan", "network": "UL", "network:wikidata": "Q7899151", "route_ref": "844", "shelter": "no", "tactile_paving": "no"}}, {"type": "node", "id": 6848140192, "lat": 59.8696596, "lon": 17.6054138, "tags": {"bench": "yes", "highway": "bus_stop", "name": "Fyrisvallsgatan", "network": "UL", "network:wikidata": "Q7899151", "route_ref": "844", "shelter": "no"}}, {"type": "node", "id": 6848140218, "lat": 59.8707021, "lon": 17.6026529, "tags": {"bench": "yes", "highway": "bus_stop", "name": "Skebogatan", "network": "UL", "route_ref": "10", "shelter": "no"}}, {"type": "node", "id": 6848140219, "lat": 59.8783573, "lon": 17.592464, "tags": {"bench": "yes", "bin": "yes", "highway": "bus_stop", "name": "S\u00f6derforsgatan", "network": "UL", "route_ref": "10", "shelter": "no"}}, {"type": "node", "id": 6848146387, "lat": 59.8820798, "lon": 17.6139574, "tags": {"bench": "yes", "bin": "yes", "highway": "bus_stop", "name": "Flott\u00f6rgatan", "network": "UL", "network:wikidata": "Q7899151", "route_ref": "8", "shelter": "no"}}, {"type": "node", "id": 6848146451, "lat": 59.8696569, "lon": 17.6177922, "tags": {"bench": "yes", "bin": "yes", "highway": "bus_stop", "lit": "yes", "local_ref": "B", "name": "Klockar\u00e4ngen", "network": "UL", "network:wikidata": "Q7899151", "route_ref": "1;10", "shelter": "no", "tactile_paving": "yes"}}, {"type": "node", "id": 6848146452, "lat": 59.8689298, "lon": 17.60762, "tags": {"bench": "yes", "bin": "no", "highway": "bus_stop", "name": "Gimogatan", "network": "UL", "route_ref": "1;10", "shelter": "no"}}, {"type": "node", "id": 6848146487, "lat": 59.8783547, "lon": 17.6186908, "tags": {"bench": "no", "bin": "no", "highway": "bus_stop", "name": "Fj\u00e4rdhundragatan", "network": "UL", "network:wikidata": "Q7899151", "route_ref": "8", "shelter": "no"}}, {"type": "node", "id": 6848146558, "lat": 59.893735, "lon": 17.615691, "tags": {"bench": "yes", "bin": "no", "gtfs:location_type:SE-UL": "0", "gtfs:parent_station:SE-UL": "9021003700317000", "gtfs:platform_code:SE-UL": "B", "gtfs:stop_id:SE-UL": "9022003700317002", "gtfs:stop_name:SE-UL": "Lilla Myrby", "highway": "bus_stop", "lit": "no", "local_ref": "B", "name": "Lilla Myrby", "nat_name": "Lilla Myrby (Uppsala)", "network": "UL", "network:wikidata": "Q7899151", "route_ref": "100;103;104;105;111;514;821", "shelter": "yes", "tactile_paving": "no"}}, {"type": "node", "id": 6848148085, "lat": 59.8855337, "lon": 17.6182079, "tags": {"bench": "no", "bin": "no", "highway": "bus_stop", "name": "B\u00e4rbygatan", "network": "UL", "network:wikidata": "Q7899151", "route_ref": "8", "shelter": "no"}}, {"type": "node", "id": 6848148127, "lat": 59.893152, "lon": 17.615677, "tags": {"bench": "no", "bin": "no", "gtfs:location_type:SE-UL": "0", "gtfs:parent_station:SE-UL": "9021003700317000", "gtfs:platform_code:SE-UL": "A", "gtfs:stop_id:SE-UL": "9022003700317001", "gtfs:stop_name:SE-UL": "Lilla Myrby", "highway": "bus_stop", "lit": "no", "local_ref": "A", "name": "Lilla Myrby", "nat_name": "Lilla Myrby (Uppsala)", "network": "UL", "network:wikidata": "Q7899151", "route_ref": "100;103;104;105;111;514;821", "shelter": "no", "tactile_paving": "no"}}, {"type": "node", "id": 6848154199, "lat": 59.8695601, "lon": 17.6177704, "tags": {"bench": "yes", "bin": "yes", "highway": "bus_stop", "lit": "yes", "local_ref": "D", "name": "Klockar\u00e4ngen", "network": "UL", "network:wikidata": "Q7899151", "route_ref": "1;10", "shelter": "yes", "tactile_paving": "yes"}}, {"type": "node", "id": 6848154201, "lat": 59.8688607, "lon": 17.6077491, "tags": {"bench": "yes", "bin": "yes", "highway": "bus_stop", "name": "Gimogatan", "network": "UL", "route_ref": "1;10", "shelter": "no"}}, {"type": "node", "id": 8708605986, "lat": 59.8679092, "lon": 17.5966591, "tags": {"railway": "milestone", "railway:position": "69"}}, {"type": "node", "id": 8708605987, "lat": 59.8679792, "lon": 17.5940895}, {"type": "node", "id": 8708605988, "lat": 59.8692583, "lon": 17.5603044}, {"type": "node", "id": 8708605989, "lat": 59.8692503, "lon": 17.5583678}, {"type": "node", "id": 8708605997, "lat": 59.8709857, "lon": 17.5256288, "tags": {"railway": "milestone", "railway:position": "73"}}, {"type": "node", "id": 8708605999, "lat": 59.8713852, "lon": 17.5078071, "tags": {"railway": "milestone", "railway:position": "74"}}, {"type": "node", "id": 8708606000, "lat": 59.8670068, "lon": 17.6144322, "tags": {"railway": "milestone", "railway:position": "68"}}, {"type": "node", "id": 8708606001, "lat": 59.8683664, "lon": 17.5788882, "tags": {"railway": "milestone", "railway:position": "70"}}, {"type": "node", "id": 8708606003, "lat": 59.8692974, "lon": 17.5611665, "tags": {"railway": "milestone", "railway:position": "71"}}, {"type": "node", "id": 8708606005, "lat": 59.8700341, "lon": 17.5433866, "tags": {"railway": "milestone", "railway:position": "72"}}, {"type": "node", "id": 8708606007, "lat": 59.8670468, "lon": 17.6144378, "tags": {"railway": "milestone", "railway:position": "68"}}, {"type": "node", "id": 8769837422, "lat": 59.8681381, "lon": 17.581822}, {"type": "node", "id": 8819072495, "lat": 59.8681053, "lon": 17.5825981}, {"type": "node", "id": 8997223115, "lat": 59.8669129, "lon": 17.6164465}, {"type": "node", "id": 9395256344, "lat": 59.8731996, "lon": 17.6082397, "tags": {"ford": "yes"}}, {"type": "node", "id": 9533011987, "lat": 59.8713731, "lon": 17.5159298, "tags": {"railway": "signal", "railway:position:exact": "73.545", "railway:signal:direction": "forward", "railway:signal:main": "SE:Mellanblocksignal", "railway:signal:main:form": "light", "railway:signal:main:function": "block", "railway:signal:position": "left", "ref": "U L4"}}, {"type": "node", "id": 9533011988, "lat": 59.8712058, "lon": 17.4980823, "tags": {"railway": "signal", "railway:position:exact": "74.545", "railway:signal:direction": "backward", "railway:signal:distant": "SE:F\u00f6rsignal", "railway:signal:distant:form": "light", "railway:signal:position": "right", "ref": "Bna L3R"}}, {"type": "node", "id": 9533011989, "lat": 59.8713734, "lon": 17.5158867, "tags": {"railway": "signal", "railway:position:exact": "73.545", "railway:signal:direction": "backward", "railway:signal:main": "SE:Mellanblocksignal", "railway:signal:main:form": "light", "railway:signal:main:function": "block", "railway:signal:position": "right", "ref": "Bna L3"}}, {"type": "node", "id": 9533086843, "lat": 59.8693932, "lon": 17.5629183}, {"type": "node", "id": 9533086844, "lat": 59.8694263, "lon": 17.564355}, {"type": "node", "id": 9533086845, "lat": 59.8694126, "lon": 17.5653584}, {"type": "node", "id": 9533086846, "lat": 59.8694227, "lon": 17.5648589}, {"type": "node", "id": 9533086848, "lat": 59.8673234, "lon": 17.6087546, "tags": {"railway": "signal", "railway:position:exact": "68.320", "railway:signal:combined": "SE:Mellansignal", "railway:signal:combined:form": "light", "railway:signal:combined:function": "intermediate", "railway:signal:direction": "forward", "railway:signal:position": "left", "ref": "U 336"}}, {"type": "node", "id": 9533086849, "lat": 59.8672839, "lon": 17.6087521, "tags": {"railway": "signal", "railway:position:exact": "68.320", "railway:signal:combined": "SE:Mellansignal", "railway:signal:combined:form": "light", "railway:signal:combined:function": "intermediate", "railway:signal:direction": "forward", "railway:signal:position": "left", "ref": "U 338"}}, {"type": "node", "id": 9533086850, "lat": 59.8669721, "lon": 17.6159726, "tags": {"railway": "signal", "railway:position:exact": "67.913", "railway:signal:combined": "SE:Mellansignal", "railway:signal:combined:form": "light", "railway:signal:combined:function": "intermediate", "railway:signal:direction": "backward", "railway:signal:position": "left", "ref": "U 331"}}, {"type": "node", "id": 9533086851, "lat": 59.8669318, "lon": 17.6159702, "tags": {"railway": "signal", "railway:position:exact": "67.913", "railway:signal:direction": "backward", "railway:signal:main": "SE:Mellansignal", "railway:signal:main:form": "light", "railway:signal:main:function": "intermediate", "railway:signal:position": "left", "ref": "U 333"}}, {"type": "node", "id": 9533086852, "lat": 59.8676266, "lon": 17.6024469, "tags": {"railway": "signal", "railway:position:exact": "68.675", "railway:signal:direction": "forward", "railway:signal:main": "SE:Utfartsblocksignal", "railway:signal:main:form": "light", "railway:signal:main:function": "exit;block", "railway:signal:position": "left", "ref": "U 342"}}, {"type": "node", "id": 9533086854, "lat": 59.8676287, "lon": 17.6024078, "tags": {"railway": "signal", "railway:position:exact": "68.675", "railway:signal:combined": "SE:Infartssignal", "railway:signal:combined:form": "light", "railway:signal:combined:function": "entry", "railway:signal:direction": "backward", "railway:signal:position": "right", "ref": "U 321"}}, {"type": "node", "id": 9533086855, "lat": 59.8680705, "lon": 17.5840134, "tags": {"railway": "signal", "railway:position:exact": "69.709", "railway:signal:direction": "backward", "railway:signal:distant": "SE:F\u00f6rsignal", "railway:signal:distant:form": "light", "railway:signal:position": "right", "ref": "U 321R"}}, {"type": "node", "id": 11144777222, "lat": 59.8851388, "lon": 17.6197755, "tags": {"bench": "yes", "bin": "no", "gtfs:platform_code:SE-UL": "B", "gtfs:stop_id:SE-UL": "9022003700537002", "gtfs:stop_name:SE-UL": "Uppsala R\u00f6bo", "highway": "bus_stop", "lit": "yes", "local_ref": "B", "name": "R\u00f6bo", "nat_name": "R\u00f6bo (Uppsala)", "network": "UL", "route_ref": "100;103;104;105;111;514;821", "shelter": "no", "tactile_paving": "yes"}}, {"type": "node", "id": 11144777223, "lat": 59.884938, "lon": 17.6194833, "tags": {"bench": "yes", "bin": "no", "gtfs:name": "Uppsala R\u00f6bo", "highway": "bus_stop", "lit": "yes", "local_ref": "A", "name": "R\u00f6bo", "nat_name": "R\u00f6bo (Uppsala)", "network": "UL", "route_ref": "100;103;104;105;111;514;821", "shelter": "yes", "tactile_paving": "yes"}}, {"type": "node", "id": 12068753059, "lat": 59.868979, "lon": 17.5712029, "tags": {"access": "no", "crossing": "no", "crossing:barrier": "no", "crossing:bell": "no", "crossing:light": "no", "railway": "crossing", "source": "survey;aerial imagery"}}, {"type": "node", "id": 12090062949, "lat": 59.8787666, "lon": 17.5800669, "tags": {"bench": "yes", "bin": "no", "highway": "bus_stop", "name": "H\u00e4sselby park", "network": "UL", "network:wikidata": "Q7899151", "route_ref": "844", "shelter": "no"}}, {"type": "node", "id": 12090062950, "lat": 59.8791718, "lon": 17.579155, "tags": {"bench": "yes", "bin": "no", "highway": "bus_stop", "name": "H\u00e4sselby park", "network": "UL", "network:wikidata": "Q7899151", "route_ref": "844", "shelter": "no"}}, {"type": "node", "id": 12090062951, "lat": 59.8836186, "lon": 17.5673211, "tags": {"bench": "no", "bin": "no", "highway": "bus_stop", "name": "H\u00e4sselby g\u00e5rd", "network": "UL", "network:wikidata": "Q7899151", "route_ref": "844", "shelter": "no"}}, {"type": "node", "id": 12090062952, "lat": 59.8847343, "lon": 17.5657815, "tags": {"bench": "no", "bin": "no", "highway": "bus_stop", "name": "H\u00e4sselby g\u00e5rd", "network": "UL", "network:wikidata": "Q7899151", "route_ref": "844", "shelter": "no"}}, {"type": "node", "id": 12090062953, "lat": 59.8896931, "lon": 17.5576758, "tags": {"bench": "no", "bin": "no", "highway": "bus_stop", "name": "Hovl\u00f6sa", "network": "UL", "network:wikidata": "Q7899151", "route_ref": "844", "shelter": "no"}}, {"type": "node", "id": 12090062954, "lat": 59.890051, "lon": 17.5574398, "tags": {"bench": "no", "bin": "no", "highway": "bus_stop", "name": "Hovl\u00f6sa", "network": "UL", "network:wikidata": "Q7899151", "route_ref": "844", "shelter": "no"}}, {"type": "node", "id": 12142313601, "lat": 59.8719497, "lon": 17.5555247, "tags": {"bench": "no", "bin": "no", "highway": "bus_stop", "name": "Sk\u00e4ggesta", "network": "UL", "route_ref": "106", "shelter": "no"}}, {"type": "node", "id": 12142313602, "lat": 59.8720008, "lon": 17.5557661, "tags": {"bench": "no", "bin": "no", "highway": "bus_stop", "name": "Sk\u00e4ggesta", "network": "UL", "route_ref": "106", "shelter": "no"}}, {"type": "node", "id": 12142313603, "lat": 59.8712025, "lon": 17.5626755, "tags": {"bench": "no", "bin": "no", "highway": "bus_stop", "name": "Nyhem", "network": "UL", "route_ref": "106", "shelter": "no"}}, {"type": "node", "id": 12142313604, "lat": 59.8712994, "lon": 17.5625038, "tags": {"bench": "no", "bin": "no", "highway": "bus_stop", "name": "Nyhem", "network": "UL", "route_ref": "106", "shelter": "no"}}, {"type": "node", "id": 12142313605, "lat": 59.8711567, "lon": 17.5694454, "tags": {"bench": "no", "bin": "no", "highway": "bus_stop", "name": "Norrg\u00e5rden", "network": "UL", "route_ref": "106", "shelter": "no"}}, {"type": "node", "id": 12142313606, "lat": 59.8705751, "lon": 17.573002, "tags": {"bench": "no", "bin": "no", "highway": "bus_stop", "name": "Norrg\u00e5rden", "network": "UL", "route_ref": "106", "shelter": "no"}}, {"type": "node", "id": 12142313607, "lat": 59.8691681, "lon": 17.5832212, "tags": {"bench": "no", "bin": "no", "highway": "bus_stop", "name": "Nyvla g\u00e5rd", "network": "UL", "route_ref": "106", "shelter": "no"}}, {"type": "node", "id": 12142313608, "lat": 59.8692381, "lon": 17.583012, "tags": {"bench": "no", "bin": "no", "highway": "bus_stop", "name": "Nyvla g\u00e5rd", "network": "UL", "route_ref": "106", "shelter": "no"}}, {"type": "node", "id": 12142313609, "lat": 59.8709608, "lon": 17.5915642, "tags": {"bench": "no", "bin": "no", "highway": "bus_stop", "name": "Husby", "network": "UL", "route_ref": "106", "shelter": "no"}}, {"type": "node", "id": 12142313610, "lat": 59.8710726, "lon": 17.5915602, "tags": {"bench": "no", "bin": "no", "highway": "bus_stop", "name": "Husby", "network": "UL", "route_ref": "106", "shelter": "no"}}, {"type": "node", "id": 12176926015, "lat": 59.8670178, "lon": 17.6048505}, {"type": "node", "id": 12176926016, "lat": 59.8671949, "lon": 17.605395}, {"type": "node", "id": 12176926017, "lat": 59.8673154, "lon": 17.6061246}, {"type": "node", "id": 12176926018, "lat": 59.8668401, "lon": 17.6043731}, {"type": "node", "id": 12176926019, "lat": 59.8665008, "lon": 17.6036382}, {"type": "node", "id": 12176926020, "lat": 59.8662503, "lon": 17.6032036}, {"type": "node", "id": 12176926021, "lat": 59.8659528, "lon": 17.6027933}, {"type": "node", "id": 12176926022, "lat": 59.8656511, "lon": 17.6025116}, {"type": "node", "id": 12427076499, "lat": 59.8697595, "lon": 17.613964, "tags": {"bin": "yes", "gtfs:platform_code:SE-UL": "A", "gtfs:stop_id:SE-UL": "9022003700566001", "highway": "bus_stop", "lit": "yes", "local_ref": "B", "name": "Seminariegatan", "network": "UL", "public_transport": "platform", "route_ref": "1", "shelter": "no", "tactile_paving": "yes"}}, {"type": "node", "id": 12427076506, "lat": 59.8696407, "lon": 17.6140532, "tags": {"bench": "yes", "bin": "yes", "gtfs:platform_code:SE-UL": "A", "gtfs:stop_id:SE-UL": "9022003700566001", "highway": "bus_stop", "lit": "yes", "local_ref": "B", "name": "Seminariegatan", "network": "UL", "network:wikidata": "Q7899151", "public_transport": "platform", "route_ref": "1", "shelter": "no", "tactile_paving": "no"}}, {"type": "node", "id": 12691841765, "lat": 59.8693687, "lon": 17.5663072}, {"type": "node", "id": 12691841766, "lat": 59.8692718, "lon": 17.5577509}, {"type": "node", "id": 12691841767, "lat": 59.8713075, "lon": 17.519213}, {"type": "node", "id": 12691841768, "lat": 59.8713312, "lon": 17.5181639, "tags": {"railway": "signal", "railway:position:exact": "73.420", "railway:signal:crossing_distant": "SE:V\u00e4gskyddsf\u00f6rsignal", "railway:signal:crossing_distant:form": "light", "railway:signal:direction": "backward", "railway:signal:position": "right"}}, {"type": "node", "id": 12691841769, "lat": 59.8706195, "lon": 17.5324188, "tags": {"railway": "signal", "railway:position:exact": "72.618", "railway:signal:crossing_distant": "SE:V\u00e4gskyddsf\u00f6rsignal", "railway:signal:crossing_distant:form": "light", "railway:signal:direction": "forward", "railway:signal:position": "right"}}, {"type": "node", "id": 12691841770, "lat": 59.8692482, "lon": 17.5585295, "tags": {"railway": "signal", "railway:position:exact": "71.148", "railway:signal:crossing_distant": "SE:V\u00e4gskyddsf\u00f6rsignal", "railway:signal:crossing_distant:form": "light", "railway:signal:direction": "forward", "railway:signal:position": "left"}}, {"type": "node", "id": 12691841771, "lat": 59.8711562, "lon": 17.5223453, "tags": {"railway": "signal", "railway:position:exact": "73.185", "railway:signal:crossing_distant": "SE:V\u00e4gskyddsf\u00f6rsignal", "railway:signal:crossing_distant:form": "light", "railway:signal:direction": "forward", "railway:signal:position": "left"}}, {"type": "node", "id": 12691841772, "lat": 59.8699404, "lon": 17.5451406, "tags": {"railway": "signal", "railway:position:exact": "71.902", "railway:signal:crossing_distant": "SE:V\u00e4gskyddsf\u00f6rsignal", "railway:signal:crossing_distant:form": "light", "railway:signal:direction": "backward", "railway:signal:position": "right"}}, {"type": "node", "id": 12691841773, "lat": 59.8688555, "lon": 17.572685, "tags": {"railway": "signal", "railway:position:exact": "70.352", "railway:signal:crossing_distant": "SE:V\u00e4gskyddsf\u00f6rsignal", "railway:signal:crossing_distant:form": "light", "railway:signal:direction": "backward", "railway:signal:position": "right"}}, {"type": "node", "id": 12691841774, "lat": 59.8713563, "lon": 17.5061301, "tags": {"railway": "signal", "railway:position:exact": "74.094", "railway:signal:crossing_distant": "SE:V\u00e4gskyddsf\u00f6rsignal", "railway:signal:crossing_distant:form": "light", "railway:signal:direction": "backward", "railway:signal:position": "right"}}, {"type": "node", "id": 12691841775, "lat": 59.8709189, "lon": 17.5268792, "tags": {"railway": "signal", "railway:position:exact": "72.930", "railway:signal:crossing": "SE:V\u00e4gskyddssignal", "railway:signal:crossing:form": "light", "railway:signal:direction": "both", "railway:signal:position": "right"}}, {"type": "node", "id": 12691841776, "lat": 59.8696486, "lon": 17.550568, "tags": {"railway": "signal", "railway:position:exact": "71.596", "railway:signal:crossing": "SE:V\u00e4gskyddssignal", "railway:signal:crossing:form": "light", "railway:signal:direction": "both", "railway:signal:position": "left"}}, {"type": "node", "id": 12691841777, "lat": 59.8713608, "lon": 17.5166472, "tags": {"railway": "signal", "railway:position:exact": "73.505", "railway:signal:crossing": "SE:V\u00e4gskyddssignal", "railway:signal:crossing:form": "light", "railway:signal:direction": "both", "railway:signal:position": "right"}}, {"type": "node", "id": 12691841778, "lat": 59.8680703, "lon": 17.5840226, "tags": {"railway": "signal", "railway:position:exact": "69.709", "railway:signal:crossing_distant": "SE:V\u00e4gskyddsf\u00f6rsignal", "railway:signal:crossing_distant:form": "light", "railway:signal:direction": "forward", "railway:signal:position": "left"}}, {"type": "node", "id": 12691841779, "lat": 59.8668911, "lon": 17.6176596, "tags": {"railway": "signal", "railway:position:exact": "67.818", "railway:signal:crossing_distant": "SE:V\u00e4gskyddsf\u00f6rsignal", "railway:signal:crossing_distant:form": "light", "railway:signal:direction": "backward", "railway:signal:position": "right"}}, {"type": "node", "id": 12691841783, "lat": 59.8677141, "lon": 17.6006705, "tags": {"railway": "signal", "railway:position:exact": "68.775", "railway:signal:crossing_distant": "SE:V\u00e4gskyddsf\u00f6rsignal", "railway:signal:crossing_distant:form": "light", "railway:signal:direction": "backward", "railway:signal:position": "right"}}, {"type": "node", "id": 12691841785, "lat": 59.8668507, "lon": 17.6176733, "tags": {"railway": "signal", "railway:position:exact": "67.818", "railway:signal:crossing_distant": "SE:V\u00e4gskyddsf\u00f6rsignal", "railway:signal:crossing_distant:form": "light", "railway:signal:direction": "backward", "railway:signal:position": "left"}}, {"type": "node", "id": 12691841787, "lat": 59.8673337, "lon": 17.6085238, "tags": {"railway": "signal", "railway:position:exact": "68.333", "railway:signal:crossing": "SE:V\u00e4gskyddssignal", "railway:signal:crossing:form": "light", "railway:signal:direction": "both", "railway:signal:position": "right"}}, {"type": "node", "id": 12691841788, "lat": 59.8684183, "lon": 17.5782239, "tags": {"railway": "signal", "railway:position:exact": "70.038", "railway:signal:crossing": "SE:V\u00e4gskyddssignal", "railway:signal:crossing:form": "light", "railway:signal:direction": "both", "railway:signal:position": "left"}}, {"type": "node", "id": 12691841789, "lat": 59.8673028, "lon": 17.6084197, "tags": {"railway": "signal", "railway:position:exact": "68.338", "railway:signal:crossing": "SE:V\u00e4gskyddssignal", "railway:signal:crossing:form": "light", "railway:signal:direction": "both", "railway:signal:position": "left"}}, {"type": "node", "id": 13295371305, "lat": 59.8669623, "lon": 17.6153445, "tags": {"disused:railway": "station", "name": "Uppsala Norra"}}, {"type": "way", "id": 30489947, "nodes": [2162467952, 2232302446, 2232302449, 2232302451, 2232302453, 2232302455, 2232302457, 2232302459, 2232302462, 2431496539], "tags": {"railway": "razed", "source": "survey;Bing"}}, {"type": "way", "id": 30490023, "nodes": [336459857, 336459860, 336459864, 336459865, 336459866], "tags": {"created_by": "Potlatch 0.10f", "railway": "disused", "source": "survey"}}, {"type": "way", "id": 206244753, "nodes": [35142941, 2162467920, 12691841779, 9533086850, 35143913, 8708606007, 2162467924, 873755498, 9533086848, 12691841787, 248723201, 2162467943, 2672743025, 2162467946, 9533086852, 9533086854, 35143915, 12691841783, 8708605986, 35144454, 8708605987, 35144455, 250034644, 12691841778, 9533086855, 35144456, 8819072495, 8769837422, 35144835, 8708606001, 12691841788, 310342173, 35144836, 12691841773, 12068753059, 35144837, 12691841765, 35146795, 9533086845, 9533086846, 9533086844, 35146796, 9533086843, 35146797, 8708606003, 8708605988, 35146798, 12691841770, 8708605989, 12691841766, 35146799, 35146800, 12691841776, 310341768, 35146801, 12691841772, 8708606005, 35146802, 312576045, 35146803, 12691841769, 35146804, 2079822025, 12691841775, 8708605997, 12691841771, 35146805, 12691841767, 12691841768, 299145538, 12691841777, 9533011987, 9533011989, 35146807, 35146809, 2162467953, 8708605999, 35146810, 12691841774, 9533011988, 35146811], "tags": {"electrified": "contact_line", "frequency": "16.67", "gauge": "1435", "maxspeed": "160", "maxspeed:sign": "130", "name": "Dalabanan", "operator": "Trafikverket", "passenger_lines": "1", "railway": "rail", "railway:atc": "yes", "railway:bidirectional": "regular", "railway:ctc": "yes", "railway:etcs": "no", "railway:preferred_direction": "both", "railway:radio": "gsm-r", "railway:rail": "continuous", "railway:traffic_mode": "mixed", "tracks": "1", "usage": "main", "voltage": "15000", "workrules": "SE:H"}}, {"type": "way", "id": 206244774, "nodes": [2162467920, 2162467918, 2162467917, 12691841785, 2162467919, 8997223115, 9533086851, 13295371305, 8708606000, 2162467934, 9533086849, 12691841789, 4242668164, 2162467941, 2672743024, 2162467944, 2162467945, 2162467946], "tags": {"gauge": "1435", "railway": "rail", "service": "siding", "source": "Bing"}}, {"type": "way", "id": 281437143, "nodes": [2431496539, 336459180, 9395256344, 336459185, 336459189, 336459194, 336459197, 336459200, 4543588033], "tags": {"highway": "path", "railway": "abandoned", "source": "survey;Bing"}}, {"type": "way", "id": 1315538941, "nodes": [248719851, 12176926022, 12176926021, 12176926020, 12176926019, 12176926018, 12176926015, 12176926016, 12176926017, 2162467944], "tags": {"abandoned:railway": "rail", "electrified": "no", "gauge": "1435", "name": "Uppsala\u2013Enk\u00f6pings J\u00e4rnv\u00e4g", "railway": "abandoned"}}]}