{"version": 0.6, "generator": "Overpass API 0.7.62.8 e802775f", "osm3s": {"timestamp_osm_base": "2026-01-12T14:42:43Z", "copyright": "The data included in this document is from www.openstreetmap.org. The data is made available under ODbL."}, "elements": [{"type": "node", "id": 247966855, "lat": 12.8772119, "lon": 77.6025994, "tags": {"amenity": "school"}}, {"type": "node", "id": 1210191549, "lat": 12.8663262, "lon": 77.5884727}, {"type": "node", "id": 1210191567, "lat": 12.8660464, "lon": 77.5888511}, {"type": "node", "id": 1210191570, "lat": 12.8663117, "lon": 77.5885461}, {"type": "node", "id": 1210191575, "lat": 12.8660398, "lon": 77.5892561}, {"type": "node", "id": 1347489613, "lat": 12.8688163, "lon": 77.5674891}, {"type": "node", "id": 1347489615, "lat": 12.8678752, "lon": 77.5668883}, {"type": "node", "id": 1347489616, "lat": 12.8685789, "lon": 77.5679072}, {"type": "node", "id": 1347489620, "lat": 12.8675928, "lon": 77.5672101}, {"type": "node", "id": 1466630506, "lat": 12.8814372, "lon": 77.5692573}, {"type": "node", "id": 1466630507, "lat": 12.8808263, "lon": 77.5685406}, {"type": "node", "id": 1466630508, "lat": 12.8807034, "lon": 77.5691092}, {"type": "node", "id": 1466630510, "lat": 12.8812463, "lon": 77.5687959}, {"type": "node", "id": 1466630512, "lat": 12.8813457, "lon": 77.5688925}, {"type": "node", "id": 1472934583, "lat": 12.867378, "lon": 77.6162668, "tags": {"addr:place": "Yelenahalli", "amenity": "school", "isced:level": "1", "name": "Government Primary School Yelenahalli", "name:kn": "\u0cb8\u0cb0\u0ccd\u0c95\u0cbe\u0cb0\u0cbf \u0caa\u0ccd\u0cb0\u0cbe\u0ca5\u0cae\u0cbf\u0c95 \u0cb6\u0cbe\u0cb2\u0cc6 \u0c8e\u0cb2\u0cc7\u0ca8\u0cb9\u0cb3\u0ccd\u0cb3\u0cbf", "operator": "Department of Education", "school": "primary"}}, {"type": "node", "id": 1506342103, "lat": 12.8195056, "lon": 77.5836591}, {"type": "node", "id": 1506342124, "lat": 12.8194939, "lon": 77.583366}, {"type": "node", "id": 1506342144, "lat": 12.8196534, "lon": 77.5839405}, {"type": "node", "id": 1506342150, "lat": 12.8203222, "lon": 77.5838975}, {"type": "node", "id": 1506342162, "lat": 12.8203201, "lon": 77.5832936}, {"type": "node", "id": 1506342171, "lat": 12.8196273, "lon": 77.5838056}, {"type": "node", "id": 1506370642, "lat": 12.811268, "lon": 77.5828585}, {"type": "node", "id": 1506370643, "lat": 12.8081242, "lon": 77.5860715}, {"type": "node", "id": 1506370644, "lat": 12.8118591, "lon": 77.5837436}, {"type": "node", "id": 1506370645, "lat": 12.8065445, "lon": 77.5857818}, {"type": "node", "id": 1506370651, "lat": 12.8069891, "lon": 77.5858623}, {"type": "node", "id": 1506370653, "lat": 12.8076131, "lon": 77.5857995}, {"type": "node", "id": 1506370655, "lat": 12.8051478, "lon": 77.5848377}, {"type": "node", "id": 1506370658, "lat": 12.8052697, "lon": 77.5846462}, {"type": "node", "id": 1506370660, "lat": 12.8043422, "lon": 77.5852454}, {"type": "node", "id": 1506370662, "lat": 12.8079061, "lon": 77.5816796}, {"type": "node", "id": 1506370666, "lat": 12.8076497, "lon": 77.5831817}, {"type": "node", "id": 1506370668, "lat": 12.8072836, "lon": 77.5833426}, {"type": "node", "id": 1506370670, "lat": 12.8082864, "lon": 77.5826653}, {"type": "node", "id": 1506370681, "lat": 12.807894, "lon": 77.5816086}, {"type": "node", "id": 1506370687, "lat": 12.8092541, "lon": 77.5814637}, {"type": "node", "id": 1506370688, "lat": 12.8086944, "lon": 77.5856531}, {"type": "node", "id": 1506370689, "lat": 12.8078208, "lon": 77.5831857}, {"type": "node", "id": 1506370691, "lat": 12.8076796, "lon": 77.5819519}, {"type": "node", "id": 1506370696, "lat": 12.805357, "lon": 77.5846177}, {"type": "node", "id": 1506370704, "lat": 12.8070482, "lon": 77.5859819}, {"type": "node", "id": 1506370707, "lat": 12.8054302, "lon": 77.5845212}, {"type": "node", "id": 1506370710, "lat": 12.8086787, "lon": 77.5861198}, {"type": "node", "id": 1506370717, "lat": 12.8081347, "lon": 77.5858945}, {"type": "node", "id": 1506370719, "lat": 12.8080159, "lon": 77.5832568}, {"type": "node", "id": 1506370720, "lat": 12.8044955, "lon": 77.5846623}, {"type": "node", "id": 1506370722, "lat": 12.8088304, "lon": 77.5818124}, {"type": "node", "id": 1506370723, "lat": 12.806602, "lon": 77.5856745}, {"type": "node", "id": 1506370724, "lat": 12.8117492, "lon": 77.5836953}, {"type": "node", "id": 1506370725, "lat": 12.8051216, "lon": 77.5855994}, {"type": "node", "id": 1506370729, "lat": 12.8110573, "lon": 77.5824858}, {"type": "node", "id": 1506370738, "lat": 12.8108547, "lon": 77.585932}, {"type": "node", "id": 1506370740, "lat": 12.8074614, "lon": 77.583187}, {"type": "node", "id": 1506370744, "lat": 12.8112695, "lon": 77.582613}, {"type": "node", "id": 1506370745, "lat": 12.8096045, "lon": 77.5817212}, {"type": "node", "id": 1506370747, "lat": 12.8075713, "lon": 77.5859283}, {"type": "node", "id": 1506370774, "lat": 12.8111231, "lon": 77.583525}, {"type": "node", "id": 1506370778, "lat": 12.8056081, "lon": 77.5844997}, {"type": "node", "id": 1506370781, "lat": 12.8063734, "lon": 77.5846891}, {"type": "node", "id": 1720796075, "lat": 12.8202592, "lon": 77.5816392}, {"type": "node", "id": 1720796200, "lat": 12.8195784, "lon": 77.5831809}, {"type": "node", "id": 1720796236, "lat": 12.8202608, "lon": 77.5825361}, {"type": "node", "id": 1720796300, "lat": 12.8194377, "lon": 77.5817427}, {"type": "node", "id": 1720796337, "lat": 12.8204119, "lon": 77.5823427}, {"type": "node", "id": 1837284567, "lat": 12.8403363, "lon": 77.5939088}, {"type": "node", "id": 1912643788, "lat": 12.8194567, "lon": 77.6008718}, {"type": "node", "id": 1912643789, "lat": 12.8193078, "lon": 77.6009269}, {"type": "node", "id": 1912643790, "lat": 12.8174141, "lon": 77.6004587}, {"type": "node", "id": 1912643791, "lat": 12.8188813, "lon": 77.5991632}, {"type": "node", "id": 1912643792, "lat": 12.819046, "lon": 77.6001396}, {"type": "node", "id": 1912643793, "lat": 12.8176501, "lon": 77.601903}, {"type": "node", "id": 1912643794, "lat": 12.8184904, "lon": 77.6013656}, {"type": "node", "id": 1912643795, "lat": 12.8173094, "lon": 77.5996514}, {"type": "node", "id": 1990604297, "lat": 12.8663637, "lon": 77.5402703}, {"type": "node", "id": 1990604302, "lat": 12.8657884, "lon": 77.5401523}, {"type": "node", "id": 1990604303, "lat": 12.8670279, "lon": 77.5395459}, {"type": "node", "id": 1990609262, "lat": 12.8657682, "lon": 77.5338585}, {"type": "node", "id": 1990609263, "lat": 12.8658477, "lon": 77.5333891}, {"type": "node", "id": 1990609264, "lat": 12.8658721, "lon": 77.5330631}, {"type": "node", "id": 1990609277, "lat": 12.8663088, "lon": 77.5331784}, {"type": "node", "id": 1990609280, "lat": 12.8669311, "lon": 77.5347492}, {"type": "node", "id": 1990609317, "lat": 12.867156, "lon": 77.5332508}, {"type": "node", "id": 1990609972, "lat": 12.8803528, "lon": 77.5461281}, {"type": "node", "id": 1990609977, "lat": 12.8806744, "lon": 77.5468657}, {"type": "node", "id": 1990609978, "lat": 12.8802168, "lon": 77.5466726}, {"type": "node", "id": 1990609982, "lat": 12.8801883, "lon": 77.5468283}, {"type": "node", "id": 2016849177, "lat": 12.8833487, "lon": 77.583754}, {"type": "node", "id": 2016849178, "lat": 12.8834186, "lon": 77.5837306}, {"type": "node", "id": 2016849179, "lat": 12.8834481, "lon": 77.5840661}, {"type": "node", "id": 2016849180, "lat": 12.8834925, "lon": 77.5839628}, {"type": "node", "id": 2016849181, "lat": 12.8836324, "lon": 77.583916}, {"type": "node", "id": 2016849182, "lat": 12.8836578, "lon": 77.5839959}, {"type": "node", "id": 2056455541, "lat": 12.8481707, "lon": 77.5886194}, {"type": "node", "id": 2083338352, "lat": 12.8815695, "lon": 77.5758606}, {"type": "node", "id": 2083338354, "lat": 12.8815753, "lon": 77.5759341}, {"type": "node", "id": 2083338356, "lat": 12.8818549, "lon": 77.5758371}, {"type": "node", "id": 2083338358, "lat": 12.8818607, "lon": 77.5759107}, {"type": "node", "id": 2173392419, "lat": 12.8803576, "lon": 77.5796579, "tags": {"addr:housenumber": "#24-39", "addr:postcode": "560078", "addr:street": "7th Main Road", "amenity": "school", "email": "communications.oisjp@orchids.edu.in", "name": "Bangalore Scottish School", "name:en": "Orchids The International School, JP Nagar", "opening_hours": "Mo-Su 09:00-18:30", "operator": "Orchids International School", "phone": "9513731352", "source": "GPS", "website": "https://www.orchidsinternationalschool.com/bangalore-branches/jp-nagar/"}}, {"type": "node", "id": 2181320618, "lat": 12.8828036, "lon": 77.5704042, "tags": {"amenity": "school", "name": "Srinidhi Public School", "source": "GPS"}}, {"type": "node", "id": 2259659279, "lat": 12.883775, "lon": 77.5947716}, {"type": "node", "id": 2259659281, "lat": 12.8841149, "lon": 77.5950387}, {"type": "node", "id": 2259659282, "lat": 12.8841229, "lon": 77.5949164}, {"type": "node", "id": 2259659283, "lat": 12.8835638, "lon": 77.5955954}, {"type": "node", "id": 2259659284, "lat": 12.8838604, "lon": 77.5956911}, {"type": "node", "id": 2259659285, "lat": 12.8839832, "lon": 77.5952136}, {"type": "node", "id": 2446754419, "lat": 12.8849765, "lon": 77.5975006}, {"type": "node", "id": 2855634916, "lat": 12.8847019, "lon": 77.5917498, "tags": {"amenity": "school", "name": "Aradhana Academy"}}, {"type": "node", "id": 2907073150, "lat": 12.8730251, "lon": 77.6260135, "tags": {"addr:city": "Begur", "addr:place": "Begur", "amenity": "school", "isced:level": "2", "name": "St Teresa Hps Begur", "name:kn": "\u0cb8\u0cc6\u0c82\u0c9f\u0ccd\u200c \u0ca4\u0cc6\u0cb0\u0cc7\u0cb8\u0cbe \u0cb9\u0cbf\u0cb0\u0cbf\u0caf \u0caa\u0ccd\u0cb0\u0cbe\u0ca5\u0cae\u0cbf\u0c95 \u0cb6\u0cbe\u0cb2\u0cc6 \u0cac\u0cc7\u0c97\u0cc2\u0cb0\u0cc1", "operator": "Department of Education", "school": "primary"}}, {"type": "node", "id": 2907073152, "lat": 12.8737507, "lon": 77.6259345, "tags": {"addr:place": "Begur", "amenity": "school", "isced:level": "3", "name": "St Teresa Hs", "name:kn": "\u0cb8\u0cc6\u0c82\u0c9f\u0ccd\u200c \u0ca4\u0cc6\u0cb0\u0cc7\u0cb8\u0cbe \u0caa\u0ccd\u0cb0\u0ccc\u0ca2\u0cb6\u0cbe\u0cb2\u0cc6, \u0cac\u0cc7\u0c97\u0cc2\u0cb0\u0cc1", "operator": "Private Un-Aided", "school": "secondary"}}, {"type": "node", "id": 2939021444, "lat": 12.8773291, "lon": 77.6000439}, {"type": "node", "id": 2939021450, "lat": 12.877078, "lon": 77.6014124}, {"type": "node", "id": 2939021455, "lat": 12.8772989, "lon": 77.6011508}, {"type": "node", "id": 2939021456, "lat": 12.8782035, "lon": 77.5984954}, {"type": "node", "id": 2939021470, "lat": 12.8774271, "lon": 77.5982298}, {"type": "node", "id": 2939021471, "lat": 12.877893, "lon": 77.5988934}, {"type": "node", "id": 2939021475, "lat": 12.8773382, "lon": 77.5993537}, {"type": "node", "id": 3125514998, "lat": 12.8844629, "lon": 77.551074}, {"type": "node", "id": 3125514999, "lat": 12.884527, "lon": 77.5510518}, {"type": "node", "id": 3125515000, "lat": 12.8845872, "lon": 77.5512344}, {"type": "node", "id": 3125515001, "lat": 12.8846102, "lon": 77.5512265}, {"type": "node", "id": 3125515002, "lat": 12.8847255, "lon": 77.5512666}, {"type": "node", "id": 3125515003, "lat": 12.884677, "lon": 77.5517237}, {"type": "node", "id": 3125515004, "lat": 12.8848056, "lon": 77.5512389}, {"type": "node", "id": 3125515005, "lat": 12.8847441, "lon": 77.5516326}, {"type": "node", "id": 3125515006, "lat": 12.8848357, "lon": 77.5516009}, {"type": "node", "id": 3125515007, "lat": 12.8849358, "lon": 77.551634}, {"type": "node", "id": 3134803465, "lat": 12.8249426, "lon": 77.6211194}, {"type": "node", "id": 3134803466, "lat": 12.8250577, "lon": 77.6204006}, {"type": "node", "id": 3134803467, "lat": 12.8240638, "lon": 77.6202531}, {"type": "node", "id": 3134803468, "lat": 12.8240037, "lon": 77.6209236}, {"type": "node", "id": 3417146657, "lat": 12.8826124, "lon": 77.6247003}, {"type": "node", "id": 3417146659, "lat": 12.882697, "lon": 77.6236133}, {"type": "node", "id": 3417146660, "lat": 12.8829613, "lon": 77.6247288}, {"type": "node", "id": 3417146661, "lat": 12.8830459, "lon": 77.6236419}, {"type": "node", "id": 3417162326, "lat": 12.8842, "lon": 77.5973998}, {"type": "node", "id": 3417162327, "lat": 12.8842023, "lon": 77.5973315}, {"type": "node", "id": 3417162334, "lat": 12.8852152, "lon": 77.5966904}, {"type": "node", "id": 3535384413, "lat": 12.8703606, "lon": 77.5926638}, {"type": "node", "id": 3535384414, "lat": 12.8705262, "lon": 77.5930496}, {"type": "node", "id": 3535384415, "lat": 12.870706, "lon": 77.5925078}, {"type": "node", "id": 3535384416, "lat": 12.8708716, "lon": 77.5928936}, {"type": "node", "id": 3535459129, "lat": 12.8815031, "lon": 77.6235621}, {"type": "node", "id": 3535459133, "lat": 12.8815167, "lon": 77.6234983}, {"type": "node", "id": 3535459159, "lat": 12.8816111, "lon": 77.6237009}, {"type": "node", "id": 3535459168, "lat": 12.8816344, "lon": 77.6235916}, {"type": "node", "id": 3535459176, "lat": 12.8816494, "lon": 77.623528}, {"type": "node", "id": 3535459188, "lat": 12.8816875, "lon": 77.623718}, {"type": "node", "id": 3535459604, "lat": 12.8817244, "lon": 77.6235449}, {"type": "node", "id": 3543380603, "lat": 12.8851139, "lon": 77.5924829}, {"type": "node", "id": 4076243858, "lat": 12.876406, "lon": 77.5984646}, {"type": "node", "id": 4076243859, "lat": 12.87644, "lon": 77.5987731}, {"type": "node", "id": 4076243860, "lat": 12.8764609, "lon": 77.5982795}, {"type": "node", "id": 4076243861, "lat": 12.8765341, "lon": 77.5995026}, {"type": "node", "id": 4076243862, "lat": 12.8765707, "lon": 77.5979872}, {"type": "node", "id": 4076243863, "lat": 12.8767789, "lon": 77.6000942}, {"type": "node", "id": 4076243864, "lat": 12.8768348, "lon": 77.600825}, {"type": "node", "id": 4076243865, "lat": 12.8768662, "lon": 77.6014177}, {"type": "node", "id": 4076243866, "lat": 12.8771224, "lon": 77.6013373}, {"type": "node", "id": 4076243867, "lat": 12.8772976, "lon": 77.601297}, {"type": "node", "id": 4076243868, "lat": 12.8775277, "lon": 77.6010234}, {"type": "node", "id": 4076243869, "lat": 12.8778284, "lon": 77.6010074}, {"type": "node", "id": 4076243870, "lat": 12.877499, "lon": 77.5979845}, {"type": "node", "id": 4076243871, "lat": 12.8781945, "lon": 77.6009564}, {"type": "node", "id": 4076243872, "lat": 12.8782389, "lon": 77.5983198}, {"type": "node", "id": 4076243873, "lat": 12.8783017, "lon": 77.6008384}, {"type": "node", "id": 4076243874, "lat": 12.8785239, "lon": 77.6005246}, {"type": "node", "id": 4076243875, "lat": 12.8786599, "lon": 77.6001678}, {"type": "node", "id": 4142629714, "lat": 12.8254731, "lon": 77.5820214}, {"type": "node", "id": 4142629715, "lat": 12.825477, "lon": 77.5824881}, {"type": "node", "id": 4279512889, "lat": 12.8819897, "lon": 77.5825547, "tags": {"addr:postcode": "560078", "addr:street": "2nd Main Road", "amenity": "school", "name": "Little Aryans"}}, {"type": "node", "id": 4483748622, "lat": 12.872083, "lon": 77.5964676}, {"type": "node", "id": 4702606094, "lat": 12.8763018, "lon": 77.6030612, "tags": {"amenity": "school", "name": "Government School", "name:en": "Govt. School", "name:kn": "\u0cb8\u0cb0\u0ccd\u0c95\u0cbe\u0cb0\u0cbf \u0cb6\u0cbe\u0cb2\u0cc6"}}, {"type": "node", "id": 4714399093, "lat": 12.8782079, "lon": 77.6026104, "tags": {"amenity": "school", "name": "Government School", "name:en": "Government School", "name:kn": "\u0cb8\u0cb0\u0ccd\u0c95\u0cbe\u0cb0\u0cbf \u0cb6\u0cbe\u0cb2\u0cc6"}}, {"type": "node", "id": 4714437394, "lat": 12.8771444, "lon": 77.6021148, "tags": {"amenity": "school", "name": "Lords School", "name:en": "Lords School"}}, {"type": "node", "id": 5378252760, "lat": 12.830147, "lon": 77.5891522}, {"type": "node", "id": 5378252761, "lat": 12.8300685, "lon": 77.5894634}, {"type": "node", "id": 5378252762, "lat": 12.8295141, "lon": 77.5895438}, {"type": "node", "id": 5378252763, "lat": 12.8295454, "lon": 77.58912}, {"type": "node", "id": 6261304459, "lat": 12.8727974, "lon": 77.5962702}, {"type": "node", "id": 6261304462, "lat": 12.8735362, "lon": 77.5979456}, {"type": "node", "id": 6261304468, "lat": 12.8730648, "lon": 77.5979793}, {"type": "node", "id": 6261304469, "lat": 12.8729388, "lon": 77.5988792}, {"type": "node", "id": 6261304472, "lat": 12.8724631, "lon": 77.5988665}, {"type": "node", "id": 6261304473, "lat": 12.8724537, "lon": 77.5986017}, {"type": "node", "id": 6261304474, "lat": 12.872093, "lon": 77.5985922}, {"type": "node", "id": 6276405887, "lat": 12.8620102, "lon": 77.5641166, "tags": {"addr:place": "Anjanapura", "amenity": "school", "isced:level": "2", "name": "GHPS Anjanapura", "name:kn": "\u0cb8\u0cb0\u0ccd\u0c95\u0cbe\u0cb0\u0cbf \u0cb9\u0cbf\u0cb0\u0cbf\u0caf \u0caa\u0ccd\u0cb0\u0cbe\u0ca5\u0cae\u0cbf\u0c95 \u0cb6\u0cbe\u0cb2\u0cc6 \u0c86\u0c82\u0c9c\u0ca8\u0caa\u0cc1\u0cb0", "operator": "Department of Education", "school": "primary"}}, {"type": "node", "id": 6346979892, "lat": 12.8841602, "lon": 77.6017702, "tags": {"addr:place": "arakere", "amenity": "school", "isced:level": "2", "name": "GHPS Arakere", "name:kn": "\u0cb8\u0cb0\u0ccd\u0c95\u0cbe\u0cb0\u0cbf \u0cb9\u0cbf\u0cb0\u0cbf\u0caf \u0caa\u0ccd\u0cb0\u0cbe\u0ca5\u0cae\u0cbf\u0c95 \u0cb6\u0cbe\u0cb2\u0cc6 \u0c85\u0cb0\u0c95\u0cc6\u0cb0\u0cc6", "operator": "Department of Education", "school": "primary"}}, {"type": "node", "id": 6348719364, "lat": 12.8722269, "lon": 77.5995362, "tags": {"addr:place": "Venugopal Nagar", "amenity": "school", "isced:level": "2", "name": "GHPS Venugopal Nagar", "name:kn": "\u0cb8\u0cb0\u0ccd\u0c95\u0cbe\u0cb0\u0cbf \u0cb9\u0cbf\u0cb0\u0cbf\u0caf \u0caa\u0ccd\u0cb0\u0cbe\u0ca5\u0cae\u0cbf\u0c95 \u0cb6\u0cbe\u0cb2\u0cc6 \u0cb5\u0cc7\u0ca3\u0cc1\u0c97\u0ccb\u0caa\u0cbe\u0cb2\u0ccd \u0ca8\u0c97\u0cb0", "operator": "Department of Education", "school": "primary"}}, {"type": "node", "id": 6348786153, "lat": 12.8590074, "lon": 77.5890223, "tags": {"addr:place": "Gottigere", "amenity": "school", "isced:level": "2", "name": "GHPS Gottigere", "name:kn": "\u0cb8\u0cb0\u0ccd\u0c95\u0cbe\u0cb0\u0cbf \u0cb9\u0cbf\u0cb0\u0cbf\u0caf \u0caa\u0ccd\u0cb0\u0cbe\u0ca5\u0cae\u0cbf\u0c95 \u0cb6\u0cbe\u0cb2\u0cc6 \u0c97\u0cca\u0c9f\u0ccd\u0c9f\u0cbf\u0c97\u0cb0\u0cc6", "operator": "Department of Education", "school": "primary"}}, {"type": "node", "id": 6348790816, "lat": 12.8572549, "lon": 77.576942, "tags": {"addr:place": "Kembathhalli", "amenity": "school", "isced:level": "2", "name": "GHPS Kembathhalli", "name:kn": "\u0cb8\u0cb0\u0ccd\u0c95\u0cbe\u0cb0\u0cbf \u0cb9\u0cbf\u0cb0\u0cbf\u0caf \u0caa\u0ccd\u0cb0\u0cbe\u0ca5\u0cae\u0cbf\u0c95 \u0cb6\u0cbe\u0cb2\u0cc6 \u0c95\u0cc6\u0c82\u0cad\u0ca4\u0ccd \u0cb9\u0cb3\u0ccd\u0cb3\u0cbf", "operator": "Department of Education", "school": "primary"}}, {"type": "node", "id": 6348900704, "lat": 12.8764315, "lon": 77.5786186, "tags": {"addr:place": "Kothanur", "amenity": "school", "isced:level": "2", "name": "GHPS Kothanur", "name:kn": "\u0cb8\u0cb0\u0ccd\u0c95\u0cbe\u0cb0\u0cbf \u0cb9\u0cbf\u0cb0\u0cbf\u0caf \u0caa\u0ccd\u0cb0\u0cbe\u0ca5\u0cae\u0cbf\u0c95 \u0cb6\u0cbe\u0cb2\u0cc6 \u0c95\u0cca\u0ca4\u0ccd\u0ca4\u0ca8\u0cc2\u0cb0\u0ccd", "operator": "Department of Education", "school": "primary"}}, {"type": "node", "id": 6349178484, "lat": 12.8655347, "lon": 77.5815146, "tags": {"addr:place": "Jambusavari Dinne", "amenity": "school", "isced:level": "2", "name": "GHPS Jambusavari Dinne", "name:kn": "\u0cb8\u0cb0\u0ccd\u0c95\u0cbe\u0cb0\u0cbf \u0cb9\u0cbf\u0cb0\u0cbf\u0caf \u0caa\u0ccd\u0cb0\u0cbe\u0ca5\u0cae\u0cbf\u0c95 \u0cb6\u0cbe\u0cb2\u0cc6 \u0c9c\u0c82\u0cac\u0cc1\u0cb8\u0cb5\u0cbe\u0cb0\u0cbf \u0ca6\u0cbf\u0ca3\u0ccd\u0ca3\u0cc6", "operator": "Department of Education", "school": "primary"}}, {"type": "node", "id": 6349188814, "lat": 12.8474735, "lon": 77.5840074, "tags": {"addr:place": "Nekarara Colony", "amenity": "school", "isced:level": "2", "name": "Jnanajyothi HPS Nekarara Colony", "name:kn": "\u0c9c\u0ccd\u0c9e\u0cbe\u0ca8\u0c9c\u0ccd\u0caf\u0ccb\u0ca4\u0cbf \u0cb9\u0cbf\u0cb0\u0cbf\u0caf \u0caa\u0ccd\u0cb0\u0cbe\u0ca5\u0cae\u0cbf\u0c95 \u0cb6\u0cbe\u0cb2\u0cc6 \u0ca8\u0cc7\u0c95\u0cbe\u0cb0\u0cb0 \u0c95\u0cbe\u0cb2\u0ccb\u0ca8\u0cbf", "operator": "Local body", "school": "primary"}}, {"type": "node", "id": 6349192885, "lat": 12.8435532, "lon": 77.5850056, "tags": {"addr:place": "Nekarara Colony", "amenity": "school", "isced:level": "2", "name": "GMPS Nekarara Colony", "name:kn": "\u0cb8\u0cb0\u0ccd\u0c95\u0cbe\u0cb0\u0cbf \u0cb9\u0cbf\u0cb0\u0cbf\u0caf \u0caa\u0ccd\u0cb0\u0cbe\u0ca5\u0cae\u0cbf\u0c95 \u0cb6\u0cbe\u0cb2\u0cc6 \u0ca8\u0cc7\u0c95\u0cbe\u0cb0\u0cb0 \u0c95\u0cbe\u0cb2\u0ccb\u0ca8\u0cbf", "operator": "Department of Education", "school": "primary"}}, {"type": "node", "id": 6349202651, "lat": 12.849598, "lon": 77.6001813}, {"type": "node", "id": 6349580757, "lat": 12.8772854, "lon": 77.5701703, "tags": {"addr:place": "Hari Nagar", "amenity": "school", "isced:level": "2", "name": "GKHPS Hari Nagar", "name:kn": "\u0cb8\u0cb0\u0ccd\u0c95\u0cbe\u0cb0\u0cbf \u0c95\u0ca8\u0ccd\u0ca8\u0ca1 \u0cb9\u0cbf\u0cb0\u0cbf\u0caf \u0caa\u0ccd\u0cb0\u0cbe\u0ca5\u0cae\u0cbf\u0c95 \u0cb6\u0cbe\u0cb2\u0cc6 \u0cb9\u0cb0\u0cbf\u0ca8\u0c97\u0cb0", "operator": "Department of Primary and Secondary Education", "operator:type": "government", "operator:wikidata": "Q111467381", "school": "primary"}}, {"type": "node", "id": 6349585531, "lat": 12.8779168, "lon": 77.5704224, "tags": {"addr:place": "Hari Nagar", "amenity": "school", "isced:level": "2", "name": "GULPS Hari Nagar", "name:kn": "\u0cb8\u0cb0\u0ccd\u0c95\u0cbe\u0cb0\u0cbf \u0c89\u0cb0\u0ccd\u0ca6\u0cc1 \u0caa\u0ccd\u0cb0\u0cbe\u0ca5\u0cae\u0cbf\u0c95 \u0cb6\u0cbe\u0cb2\u0cc6 \u0cb9\u0cb0\u0cbf\u0ca8\u0c97\u0cb0", "operator": "Department of Education", "school": "primary"}}, {"type": "node", "id": 6349589920, "lat": 12.8763234, "lon": 77.6028969, "tags": {"amenity": "school", "isced:level": "2", "name": "GMPS Hulimavu", "name:kn": "\u0cb8\u0cb0\u0ccd\u0c95\u0cbe\u0cb0\u0cbf \u0cae\u0cbe\u0ca6\u0cb0\u0cbf \u0caa\u0ccd\u0cb0\u0cbe\u0ca5\u0cae\u0cbf\u0c95 \u0cb6\u0cbe\u0cb2\u0cc6 \u0cb9\u0cc1\u0cb3\u0cbf\u0cae\u0cbe\u0cb5\u0cc1", "operator": "Department of Education", "school": "primary"}}, {"type": "node", "id": 6351593514, "lat": 12.8841864, "lon": 77.5924192}, {"type": "node", "id": 6351593515, "lat": 12.8845693, "lon": 77.5913442}, {"type": "node", "id": 6351593516, "lat": 12.8853877, "lon": 77.5915454}, {"type": "node", "id": 6351593517, "lat": 12.885037, "lon": 77.5927549}, {"type": "node", "id": 6400386412, "lat": 12.8586411, "lon": 77.5626375, "tags": {"addr:place": "Anjanapura", "amenity": "school", "isced:level": "3", "name": "Florence Public School 4th Blk, Anjanapura", "name:kn": "\u0cab\u0ccd\u0cb2\u0cbe\u0cb0\u0cc6\u0ca8\u0ccd\u0cb8\u0ccd \u0caa\u0cac\u0ccd\u0cb2\u0cbf\u0c95\u0ccd \u0cb6\u0cbe\u0cb2\u0cc6 \u0cea\u0ca8\u0cc7 \u0cac\u0ccd\u0cb2\u0cbe\u0c95\u0ccd, \u0c86\u0c82\u0c9c\u0ca8\u0cbe\u0caa\u0cc1\u0cb0", "operator": "Private Un-Aided", "school": "Higher Secondary"}}, {"type": "node", "id": 6400392576, "lat": 12.8598087, "lon": 77.5677765, "tags": {"addr:place": "Anjanapura", "amenity": "school", "isced:level": "3", "name": "Mvs HPS, Anjanapura", "name:kn": "\u0c8e\u0c82.\u0cb5\u0cbf.\u0c8e\u0cb8\u0ccd \u0cb9\u0cbf\u0cb0\u0cbf\u0caf \u0caa\u0ccd\u0cb0\u0cbe\u0ca5\u0cae\u0cbf\u0c95 \u0cb6\u0cbe\u0cb2\u0cc6 ,\u0c86\u0c82\u0c9c\u0ca8\u0cbe\u0caa\u0cc1\u0cb0", "operator": "Private Un-Aided", "school": "Higher secondary"}}, {"type": "node", "id": 6405552609, "lat": 12.8847701, "lon": 77.6080296, "tags": {"addr:place": "Arakere", "amenity": "school", "isced:level": "3", "name": "Divya Jyothi HS, Arakere", "name:kn": "\u0ca6\u0cbf\u0cb5\u0ccd\u0caf \u0c9c\u0ccd\u0caf\u0ccb\u0ca4\u0cbf \u0caa\u0ccd\u0cb0\u0ccc\u0ca2\u0cb6\u0cbe\u0cb2\u0cc6, \u0c85\u0cb0\u0c95\u0cc6\u0cb0\u0cc6", "operator": "Private Un-Aided", "school": "Higher secondary"}}, {"type": "node", "id": 6405566811, "lat": 12.884049, "lon": 77.6042452, "tags": {"addr:place": "Arakere", "amenity": "school", "isced:level": "2", "name": "J P Vidyakendra School, Arakere", "name:kn": "\u0c9c\u0cc6.\u0caa\u0cbf. \u0cb5\u0cbf\u0ca6\u0ccd\u0caf\u0cbe\u0c95\u0cc7\u0c82\u0ca6\u0ccd\u0cb0 \u0cb6\u0cbe\u0cb2\u0cc6, \u0c85\u0cb0\u0c95\u0cc6\u0cb0\u0cc6", "operator": "Private Un-Aided", "school": "Upper primary"}}, {"type": "node", "id": 6406118217, "lat": 12.884934, "lon": 77.5906518, "tags": {"addr:place": "Arakere", "amenity": "school", "isced:level": "1", "name": "Shine Eng School, Arakere", "name:kn": "\u0cb6\u0cc8\u0ca8\u0ccd \u0c86\u0c82\u0c97\u0ccd\u0cb2 \u0cb6\u0cbe\u0cb2\u0cc6, \u0c85\u0cb0\u0c95\u0cc6\u0cb0\u0cc6", "operator": "Private Un-Aided", "school": "primary"}}, {"type": "node", "id": 6406180475, "lat": 12.8846325, "lon": 77.5920843, "tags": {"addr:place": "Arakere", "amenity": "school", "isced:level": "3", "name": "Aradhana EHPS Arakere, Arakere", "name:kn": "\u0c86\u0cb0\u0cbe\u0ca7\u0ca8 \u0c86\u0c82\u0c97\u0ccd\u0cb2 \u0cb9\u0cbf\u0cb0\u0cbf\u0caf \u0caa\u0ccd\u0cb0\u0cbe\u0ca5\u0cae\u0cbf\u0c95 \u0cb6\u0cbe\u0cb2\u0cc6 \u0c85\u0cb0\u0c95\u0cc6\u0cb0\u0cc6", "operator": "Private Un-Aided", "school": "Higher secondary"}}, {"type": "node", "id": 6406272357, "lat": 12.8844411, "lon": 77.5965435}, {"type": "node", "id": 6422302288, "lat": 12.8450701, "lon": 77.5941913, "tags": {"addr:place": "Basavanapura", "amenity": "school", "isced:level": "3", "name": "GLPS Basavanapura", "name:kn": "\u0cb8\u0cb0\u0ccd\u0c95\u0cbe\u0cb0\u0cbf \u0c95\u0cbf\u0cb0\u0cbf\u0caf \u0caa\u0ccd\u0cb0\u0cbe\u0ca5\u0cae\u0cbf\u0c95 \u0cb6\u0cbe\u0cb2\u0cc6 \u0cac\u0cb8\u0cb5\u0ca8\u0caa\u0cc1\u0cb0", "operator": "Department of Education", "school": "Higher Primary"}}, {"type": "node", "id": 6422309510, "lat": 12.8439382, "lon": 77.5959453, "tags": {"addr:place": "Basavanapura", "amenity": "school", "isced:level": "3", "name": "Jnanabindu, Basavanapura", "name:kn": "\u0c9c\u0ccd\u0c9e\u0cbe\u0ca8\u0cac\u0cbf\u0c82\u0ca6\u0cc1, \u0cac\u0cb8\u0cb5\u0ca8\u0caa\u0cc1\u0cb0", "operator": "Private Un-Aided", "school": "Higher secondary"}}, {"type": "node", "id": 6430489237, "lat": 12.8729296, "lon": 77.6128346}, {"type": "node", "id": 6430493134, "lat": 12.8780562, "lon": 77.6167931, "tags": {"addr:place": "Begur", "amenity": "school", "isced": "1", "name": "St Pauls School, Begur", "name:kn": "\u0cb8\u0cc6\u0c82\u0c9f\u0ccd \u0caa\u0cbe\u0cb2\u0ccd\u0cb8\u0ccd \u0cb6\u0cbe\u0cb2\u0cc6,\u0cac\u0cc7\u0c97\u0cc2\u0cb0\u0cc1", "operator": "Private Un-Aided", "school": "primary"}}, {"type": "node", "id": 6430508829, "lat": 12.8376165, "lon": 77.6197366, "tags": {"addr:place": "Begur", "amenity": "school", "isced:level": "3", "name": "Preethidhama, Begur", "name:kn": "\u0caa\u0ccd\u0cb0\u0cc0\u0ca4\u0cbf\u0ca7\u0cbe\u0cae,\u0cac\u0cc7\u0c97\u0cc2\u0cb0\u0cc1", "operator": "Private Un-Aided", "school": "Higher Secondary"}}, {"type": "node", "id": 6437600296, "lat": 12.8514983, "lon": 77.6204097, "tags": {"addr:place": "Begur", "amenity": "school", "isced:level": "1", "name": "GLPS Mylasandra, Begur", "name:kn": "\u0cb8\u0cb0\u0ccd\u0c95\u0cbe\u0cb0\u0cbf \u0c95\u0cbf\u0cb0\u0cbf\u0caf \u0caa\u0ccd\u0cb0\u0cbe\u0ca5\u0cae\u0cbf\u0c95 \u0cb6\u0cbe\u0cb2\u0cc6 \u0cae\u0cc8\u0cb2\u0cb8\u0c82\u0ca6\u0ccd\u0cb0, \u0cac\u0cc7\u0c97\u0cc2\u0cb0\u0cc1", "operator": "Department of Education", "school": "Primary Only"}}, {"type": "node", "id": 6437807460, "lat": 12.8838456, "lon": 77.5952932, "tags": {"addr:place": "Bommana Halli cmc", "amenity": "school", "isced:level": "3", "name": "Janak Vidyalaya, Bommana Halli Cmc", "name:kn": "\u0c9c\u0ca8\u0c95\u0ccd \u0cb5\u0cbf\u0ca6\u0ccd\u0caf\u0cbe\u0cb2\u0caf,\u0cac\u0cca\u0cae\u0ccd\u0cae\u0ca8\u0cb9\u0cb3\u0ccd\u0cb3\u0cbf \u0cb8\u0cbf.\u0c8e\u0c82.\u0cb8\u0cbf", "operator": "Private Un-Aided", "school": "Higher Secondary"}}, {"type": "node", "id": 6496798356, "lat": 12.8569301, "lon": 77.5854776, "tags": {"addr:place": "Gottigere", "amenity": "school", "isced:level": "3", "name": "Silicon Vally LPS Gottigere", "name:kn": "\u0cb8\u0cbf\u0cb2\u0cbf\u0c95\u0cbe\u0ca8\u0ccd \u0cb5\u0ccd\u0caf\u0cbe\u0cb2\u0cbf \u0c95\u0cbf\u0cb0\u0cbf\u0caf \u0caa\u0ccd\u0cb0\u0cbe\u0ca5\u0cae\u0cbf\u0c95 \u0cb6\u0cbe\u0cb2\u0cc6 \u0c97\u0cca\u0c9f\u0ccd\u0c9f\u0cbf\u0c97\u0cc6\u0cb0\u0cc6", "operator": "Private Un-Aided", "school": "Higher Secondary"}}, {"type": "node", "id": 6496810726, "lat": 12.8656934, "lon": 77.5860168, "tags": {"addr:place": "Gottigere", "amenity": "school", "isced:level": "2", "name": "Sri Ramakrishna C E Kendra,Gottigere", "name:kn": "\u0cb6\u0ccd\u0cb0\u0cc0 \u0cb0\u0cbe\u0cae\u0c95\u0cc3\u0cb7\u0ccd\u0ca3 \u0cb8\u0cbf \u0c87 \u0c95\u0cc7\u0c82\u0ca6\u0ccd\u0cb0 \u0c97\u0cca\u0c9f\u0ccd\u0c9f\u0cbf\u0c97\u0cc6\u0cb0\u0cc6", "operator": "Private Aided", "school": "Higher Primary"}}, {"type": "node", "id": 6496814726, "lat": 12.8525231, "lon": 77.5877651, "tags": {"addr:place": "Gottigere", "amenity": "school", "isced:level": "3", "name": "GHS Gottigere", "name:kn": "\u0cb8\u0cb0\u0ccd\u0c95\u0cbe\u0cb0\u0cbf \u0caa\u0ccd\u0cb0\u0ccc\u0ca2\u0cb6\u0cbe\u0cb2\u0cc6 \u0c97\u0cca\u0c9f\u0ccd\u0c9f\u0cbf\u0c97\u0cc6\u0cb0\u0cc6", "operator": "Department of Education", "school": "Higher Secondary"}}, {"type": "node", "id": 6496824065, "lat": 12.8546645, "lon": 77.5879146, "tags": {"addr:place": "Gottigere", "amenity": "school", "isced:level": "2", "name": "Little Angels, Gottigere", "name:kn": "\u0cb2\u0cbf\u0c9f\u0cb2\u0ccd \u0c8f\u0c82\u0c9c\u0cb2\u0ccd,\u0c97\u0cca\u0c9f\u0ccd\u0c9f\u0cbf\u0c97\u0cc6\u0cb0\u0cc6", "operator": "Private Un-Aided", "school": "Higher Primary"}}, {"type": "node", "id": 6496835649, "lat": 12.859947, "lon": 77.590048, "tags": {"addr:place": "Gottigere", "amenity": "school", "isced:level": "3", "name": "Sudarshan Public School (cbse), Gottigere", "name:kn": "\u0cb8\u0cc1\u0ca6\u0cb0\u0ccd\u0cb6\u0ca8\u0ccd \u0caa\u0cac\u0ccd\u0cb2\u0cbf\u0c95\u0ccd \u0c8e\u0cb8\u0ccd.\u0cb8\u0cbf.\u0c8e\u0c9a\u0ccd (\u0cb8\u0cbf.\u0cac\u0cbf.\u0c8e\u0cb8\u0ccd.\u0c87), \u0c97\u0cca\u0c9f\u0ccd\u0c9f\u0cbf\u0c97\u0cc6\u0cb0\u0cc6", "operator": "Private Un-Aided", "school": "Higher Secondary"}}, {"type": "node", "id": 6536353060, "lat": 12.8773193, "lon": 77.5834526, "tags": {"addr:place": "Kothanur", "amenity": "school", "isced:level": "3", "name": "The Little Angels School, Kothanur", "name:kn": "\u0cb2\u0cbf\u0c9f\u0cb2\u0ccd \u0c8f\u0c82\u0c9c\u0cb2\u0ccd \u0cb6\u0cbe\u0cb2\u0cc6,\u0c95\u0cca\u0ca4\u0ccd\u0ca4\u0ca8\u0cc2\u0cb0\u0cc1", "operator": "Private Un-Aided", "school": "Higher Secondary"}}, {"type": "node", "id": 6536359408, "lat": 12.881709, "lon": 77.5759556, "tags": {"addr:place": "Kothanur", "amenity": "school", "isced:level": "3", "name": "Sri Maruthi Edu Trust School Kothanur", "name:kn": "\u0cb6\u0ccd\u0cb0\u0cc0 \u0cae\u0cbe\u0cb0\u0cc1\u0ca4\u0cbf \u0c95\u0cca\u0ca4\u0ccd\u0ca4\u0ca8\u0cc2\u0cb0\u0cc1 \u0c8e\u0c9c\u0cc1\u0c95\u0cc7\u0cb6\u0ca8\u0ccd \u0c9f\u0ccd\u0cb0\u0cb8\u0ccd\u0c9f\u0ccd \u0c95\u0cca\u0ca4\u0ccd\u0ca4\u0ca8\u0cc2\u0cb0\u0cc1", "operator": "Private Un-Aided", "school": "Higher Secondary"}}, {"type": "node", "id": 6536363498, "lat": 12.8732088, "lon": 77.5744133, "tags": {"addr:place": "Kothanur", "amenity": "school", "isced:level": "1", "name": "Sri Sarathy English School, Kothanur", "name:kn": "\u0cb6\u0ccd\u0cb0\u0cc0 \u0cb8\u0cbe\u0cb0\u0ca5\u0cbf \u0c86\u0c82\u0c97\u0ccd\u0cb2 \u0cb6\u0cbe\u0cb2\u0cc6,\u0c95\u0cca\u0ca4\u0ccd\u0ca4\u0ca8\u0cc2\u0cb0\u0cc1", "operator": "Private Un-Aided", "school": "primary"}}, {"type": "node", "id": 6536364433, "lat": 12.8767474, "lon": 77.5725941, "tags": {"addr:place": "Kothanur", "amenity": "school", "isced:level": "3", "name": "Ennar School Aadithya Nagar, Kothanur", "name:kn": "\u0c8e\u0ca8\u0ccd\u0ca8\u0cbe\u0cb0\u0ccd \u0cb6\u0cbe\u0cb2\u0cc6 \u0c86\u0ca6\u0cbf\u0ca4\u0ccd\u0caf \u0ca8\u0c97\u0cb0, \u0c95\u0cca\u0ca4\u0ccd\u0ca4\u0ca8\u0cc2\u0cb0\u0cc1", "operator": "Private Un-Aided", "school": "Higher Secondary"}}, {"type": "node", "id": 6536381254, "lat": 12.8755011, "lon": 77.5806222, "tags": {"addr:place": "Kothanur", "amenity": "school", "isced:level": "2", "name": "A E T School Sree Annapoornesh, Kothanur", "name:kn": "\u0c8e.\u0c87.\u0c9f\u0cbf. \u0cb6\u0cbe\u0cb2\u0cc6 \u0cb6\u0ccd\u0cb0\u0cc0 \u0c85\u0ca8\u0ccd\u0ca8\u0caa\u0cc2\u0cb0\u0ccd\u0ca3\u0cc7\u0cb6\u0ccd,\u0c95\u0cca\u0ca4\u0ccd\u0ca4\u0ca8\u0cc2\u0cb0\u0cc1", "operator": "Private Un-Aided", "school": "Higher primary"}}, {"type": "node", "id": 6536384146, "lat": 12.8825158, "lon": 77.5758676, "tags": {"addr:place": "Kothanur", "amenity": "school", "isced:level": "3", "name": "Glissy Public School, Kothanur", "name:kn": "\u0c97\u0ccd\u0cb2\u0cbf\u0cb8\u0cbf \u0caa\u0cac\u0ccd\u0cb2\u0cbf\u0c95\u0ccd \u0cb6\u0cbe\u0cb2\u0cc6,\u0c95\u0cca\u0ca4\u0ccd\u0ca4\u0ca8\u0cc2\u0cb0\u0cc1", "operator": "Private Un-Aided", "school": "Higher Secondary"}}, {"type": "node", "id": 6536386707, "lat": 12.8833878, "lon": 77.5837275, "tags": {"addr:place": "Kothanur", "amenity": "school", "isced:level": "3", "name": "Lady Wellington School, Kothanur", "name:kn": "\u0cb2\u0cc7\u0ca1\u0cbf \u0cb5\u0cc6\u0cb2\u0ccd\u0cb2\u0cbf\u0c82\u0c97\u0ccd\u0c9f\u0ca8\u0ccd \u0cb6\u0cbe\u0cb2\u0cc6, \u0c95\u0cca\u0ca4\u0ccd\u0ca4\u0ca8\u0cc2\u0cb0\u0cc1", "operator": "Private Un-Aided", "school": "Higher Secondary"}}, {"type": "node", "id": 6536406541, "lat": 12.8787866, "lon": 77.5777581, "tags": {"addr:place": "Kothanur", "amenity": "school", "isced:level": "3", "name": "Jnanavikas HPS, Kothanur", "name:kn": "\u0c9c\u0ccd\u0c9e\u0cbe\u0ca8 \u0cb5\u0cbf\u0c95\u0cbe\u0cb8\u0ccd \u0cb9\u0cbf\u0cb0\u0cbf\u0caf \u0caa\u0ccd\u0cb0\u0cbe\u0ca5\u0cae\u0cbf\u0c95 \u0cb6\u0cbe\u0cb2\u0cc6, \u0c95\u0cca\u0ca4\u0ccd\u0ca4\u0ca8\u0cc2\u0cb0\u0cc1", "operator": "Private Un-Aided", "school": "Higher Secondary"}}, {"type": "node", "id": 6536421096, "lat": 12.8686079, "lon": 77.5841946, "tags": {"addr:place": "Kothanur", "amenity": "school", "isced:level": "2", "name": "Vidyakirana Public School, Kothanur", "name:kn": "\u0cb5\u0cbf\u0ca6\u0ccd\u0caf\u0cbe\u0c95\u0cbf\u0cb0\u0ca3 \u0caa\u0cac\u0ccd\u0cb2\u0cbf\u0c95\u0ccd \u0cb6\u0cbe\u0cb2\u0cc6 \u0c95\u0cca\u0ca4\u0ccd\u0ca4\u0ca8\u0cc2\u0cb0\u0cc1", "operator": "Private Un-Aided", "school": "Higher primary"}}, {"type": "node", "id": 6536612869, "lat": 12.8779934, "lon": 77.5846361, "tags": {"addr:place": "Kothanur", "amenity": "school", "isced:level": "2", "name": "Clever Land Kottanuru Dinne, Kothanur", "name:kn": "\u0c95\u0ccd\u0cb2\u0cb5\u0cc6\u0cb0\u0ccd \u0cb2\u0ccd\u0caf\u0cbe\u0c82\u0ca1\u0ccd \u0ca6\u0cbf\u0ca3\u0ccd\u0ca3\u0cc6 \u0c95\u0cca\u0ca4\u0ccd\u0ca4\u0ca8\u0cc2\u0cb0\u0cc1", "operator": "Private Un-Aided", "school": "Higher Primary"}}, {"type": "node", "id": 6681252707, "lat": 12.8738653, "lon": 77.5589454}, {"type": "node", "id": 6681252708, "lat": 12.8735429, "lon": 77.5596766}, {"type": "node", "id": 6681252709, "lat": 12.8742204, "lon": 77.5600852}, {"type": "node", "id": 6681252710, "lat": 12.8742966, "lon": 77.5593168}, {"type": "node", "id": 6681285587, "lat": 12.8743114, "lon": 77.559466}, {"type": "node", "id": 6681297603, "lat": 12.874328, "lon": 77.5596568}, {"type": "node", "id": 6745463978, "lat": 12.8493518, "lon": 77.5819746, "tags": {"addr:place": "Pillagana Halli", "amenity": "school", "isced:level": "1", "name": "GLPS Pillagana Halli", "name:kn": "\u0cb8\u0cb0\u0ccd\u0c95\u0cbe\u0cb0\u0cbf \u0c95\u0cbf\u0cb0\u0cbf\u0caf \u0caa\u0ccd\u0cb0\u0cbe\u0ca5\u0cae\u0cbf\u0c95 \u0cb6\u0cbe\u0cb2\u0cc6 \u0caa\u0cbf\u0cb3\u0ccd\u0cb3\u0c97\u0ca8\u0cb9\u0cb3\u0ccd\u0cb3\u0cbf", "operator": "Department of Education", "school": "primary"}}, {"type": "node", "id": 7236242031, "lat": 12.8833258, "lon": 77.5593728}, {"type": "node", "id": 7236242032, "lat": 12.8831454, "lon": 77.5599897}, {"type": "node", "id": 7236242033, "lat": 12.8829938, "lon": 77.5612316}, {"type": "node", "id": 7236242034, "lat": 12.8832474, "lon": 77.5618377}, {"type": "node", "id": 7236242035, "lat": 12.8834226, "lon": 77.5599521}, {"type": "node", "id": 7236242036, "lat": 12.8835324, "lon": 77.5594291}, {"type": "node", "id": 7236242083, "lat": 12.8834121, "lon": 77.5618752}, {"type": "node", "id": 7236242084, "lat": 12.8836997, "lon": 77.5600165}, {"type": "node", "id": 7236242191, "lat": 12.8772152, "lon": 77.5680417}, {"type": "node", "id": 7236242192, "lat": 12.8782402, "lon": 77.5685191}, {"type": "node", "id": 7298163585, "lat": 12.848586, "lon": 77.5420202}, {"type": "node", "id": 7298163634, "lat": 12.846903, "lon": 77.5432193}, {"type": "node", "id": 7298163635, "lat": 12.8469141, "lon": 77.5419251}, {"type": "node", "id": 7298163651, "lat": 12.8478603, "lon": 77.5420001}, {"type": "node", "id": 7298163652, "lat": 12.8489377, "lon": 77.5420591}, {"type": "node", "id": 7298163653, "lat": 12.8487913, "lon": 77.5436309}, {"type": "node", "id": 7298163654, "lat": 12.8484748, "lon": 77.5437677}, {"type": "node", "id": 7298163655, "lat": 12.8479074, "lon": 77.543706}, {"type": "node", "id": 7298163656, "lat": 12.8479074, "lon": 77.5433466}, {"type": "node", "id": 7298163657, "lat": 12.8469869, "lon": 77.5432205}, {"type": "node", "id": 7298163658, "lat": 12.8458389, "lon": 77.5432044}, {"type": "node", "id": 7298163659, "lat": 12.8448242, "lon": 77.5431722}, {"type": "node", "id": 7298163660, "lat": 12.8448425, "lon": 77.5429255}, {"type": "node", "id": 7298163661, "lat": 12.843688, "lon": 77.5426452}, {"type": "node", "id": 7298163662, "lat": 12.8437599, "lon": 77.5419009}, {"type": "node", "id": 7298163663, "lat": 12.8438619, "lon": 77.5418231}, {"type": "node", "id": 7298163664, "lat": 12.8439978, "lon": 77.5418016}, {"type": "node", "id": 7298163665, "lat": 12.8440894, "lon": 77.5417587}, {"type": "node", "id": 7331742667, "lat": 12.819539, "lon": 77.6195079}, {"type": "node", "id": 7331742668, "lat": 12.8195586, "lon": 77.6194932}, {"type": "node", "id": 7331742669, "lat": 12.8206292, "lon": 77.6199181}, {"type": "node", "id": 7331742673, "lat": 12.8204295, "lon": 77.621706}, {"type": "node", "id": 7331742676, "lat": 12.8205132, "lon": 77.6212808}, {"type": "node", "id": 7331742678, "lat": 12.8206204, "lon": 77.6194999}, {"type": "node", "id": 7331742688, "lat": 12.8201861, "lon": 77.6219117}, {"type": "node", "id": 7331742696, "lat": 12.8201943, "lon": 77.6223224}, {"type": "node", "id": 7331742697, "lat": 12.8197436, "lon": 77.6222565}, {"type": "node", "id": 7331742701, "lat": 12.819603, "lon": 77.6220317}, {"type": "node", "id": 7331742710, "lat": 12.8194082, "lon": 77.6217201}, {"type": "node", "id": 7682106724, "lat": 12.8728178, "lon": 77.5911911}, {"type": "node", "id": 7682106731, "lat": 12.87357, "lon": 77.5911502}, {"type": "node", "id": 7682106734, "lat": 12.8731833, "lon": 77.5899231}, {"type": "node", "id": 7928087585, "lat": 12.8401824, "lon": 77.5945365}, {"type": "node", "id": 8375016087, "lat": 12.8201136, "lon": 77.6194959}, {"type": "node", "id": 8809336714, "lat": 12.8777003, "lon": 77.5853151}, {"type": "node", "id": 9892036293, "lat": 12.8730185, "lon": 77.6116571}, {"type": "node", "id": 9892036294, "lat": 12.8743959, "lon": 77.6117932}, {"type": "node", "id": 9892036295, "lat": 12.8743677, "lon": 77.6126227}, {"type": "node", "id": 9919570146, "lat": 12.8777329, "lon": 77.5855887}, {"type": "node", "id": 9919570153, "lat": 12.8727244, "lon": 77.593009}, {"type": "node", "id": 9919570156, "lat": 12.8727064, "lon": 77.5911971}, {"type": "node", "id": 9919570158, "lat": 12.8715595, "lon": 77.5923237}, {"type": "node", "id": 9919570159, "lat": 12.8711306, "lon": 77.5926349}, {"type": "node", "id": 9919570160, "lat": 12.8712378, "lon": 77.5928816}, {"type": "node", "id": 9919570161, "lat": 12.8711829, "lon": 77.5933161}, {"type": "node", "id": 9919570162, "lat": 12.8728028, "lon": 77.5939398}, {"type": "node", "id": 9919570163, "lat": 12.873698, "lon": 77.5911433}, {"type": "node", "id": 9919570164, "lat": 12.8724014, "lon": 77.5911918}, {"type": "node", "id": 9919570165, "lat": 12.8722637, "lon": 77.5900114}, {"type": "node", "id": 9919570195, "lat": 12.8641987, "lon": 77.5837406}, {"type": "node", "id": 9919570199, "lat": 12.8658369, "lon": 77.5858355}, {"type": "node", "id": 9919570200, "lat": 12.8662853, "lon": 77.5842503}, {"type": "node", "id": 9919570222, "lat": 12.8668214, "lon": 77.5879839}, {"type": "node", "id": 9919570223, "lat": 12.8672999, "lon": 77.5881529}, {"type": "node", "id": 9919570224, "lat": 12.8670436, "lon": 77.5897247}, {"type": "node", "id": 9919570225, "lat": 12.8666349, "lon": 77.5898763}, {"type": "node", "id": 9919570226, "lat": 12.8673731, "lon": 77.5886625}, {"type": "node", "id": 9919570227, "lat": 12.8670541, "lon": 77.5873804}, {"type": "node", "id": 9919570228, "lat": 12.8668972, "lon": 77.5878257}, {"type": "node", "id": 9919570229, "lat": 12.8667142, "lon": 77.5872731}, {"type": "node", "id": 9919570234, "lat": 12.8703417, "lon": 77.5898824}, {"type": "node", "id": 9919570235, "lat": 12.8689063, "lon": 77.5925659}, {"type": "node", "id": 9919570236, "lat": 12.8690537, "lon": 77.5920554}, {"type": "node", "id": 9919570237, "lat": 12.8700068, "lon": 77.5923481}, {"type": "node", "id": 9919570238, "lat": 12.8698524, "lon": 77.5928771}, {"type": "node", "id": 9919570240, "lat": 12.8673914, "lon": 77.590583}, {"type": "node", "id": 9919570241, "lat": 12.8672385, "lon": 77.5919951}, {"type": "node", "id": 9919570242, "lat": 12.8710522, "lon": 77.5932598}, {"type": "node", "id": 9919570243, "lat": 12.8711123, "lon": 77.5928333}, {"type": "node", "id": 9919570244, "lat": 12.8709528, "lon": 77.5924873}, {"type": "node", "id": 9919570245, "lat": 12.8711803, "lon": 77.5915834}, {"type": "node", "id": 9919570246, "lat": 12.8694362, "lon": 77.5880456}, {"type": "node", "id": 9970411103, "lat": 12.8269599, "lon": 77.5845506}, {"type": "node", "id": 9970411104, "lat": 12.8267324, "lon": 77.5864604}, {"type": "node", "id": 9970411105, "lat": 12.8274934, "lon": 77.586734}, {"type": "node", "id": 9970411106, "lat": 12.8277497, "lon": 77.5845882}, {"type": "node", "id": 10083914301, "lat": 12.8093661, "lon": 77.5789306, "tags": {"amenity": "school", "check_date": "2022-10-08", "name": "Shree Sai Sadhbhavaana School"}}, {"type": "node", "id": 10185153752, "lat": 12.8203611, "lon": 77.6194979}, {"type": "node", "id": 10220948541, "lat": 12.860917, "lon": 77.6102704}, {"type": "node", "id": 10233431244, "lat": 12.875934, "lon": 77.5620496}, {"type": "node", "id": 10242924636, "lat": 12.8739572, "lon": 77.6260002}, {"type": "node", "id": 10242924637, "lat": 12.8731493, "lon": 77.6260659}, {"type": "node", "id": 10242924638, "lat": 12.8731876, "lon": 77.626525}, {"type": "node", "id": 10570186219, "lat": 12.8108712, "lon": 77.585896}, {"type": "node", "id": 10579312528, "lat": 12.8726158, "lon": 77.5988645}, {"type": "node", "id": 10697710348, "lat": 12.8632547, "lon": 77.589131}, {"type": "node", "id": 10697710349, "lat": 12.8624556, "lon": 77.5888039}, {"type": "node", "id": 10697710350, "lat": 12.8617875, "lon": 77.5902882}, {"type": "node", "id": 10697710351, "lat": 12.8623113, "lon": 77.5903846}, {"type": "node", "id": 10697710352, "lat": 12.8626806, "lon": 77.5897785}, {"type": "node", "id": 10697710353, "lat": 12.8628854, "lon": 77.5898095}, {"type": "node", "id": 10697710358, "lat": 12.8621501, "lon": 77.5911663}, {"type": "node", "id": 10697710446, "lat": 12.8467843, "lon": 77.588472}, {"type": "node", "id": 10697710447, "lat": 12.8466911, "lon": 77.5896471}, {"type": "node", "id": 10697710448, "lat": 12.8475105, "lon": 77.5897028}, {"type": "node", "id": 10697710449, "lat": 12.8475067, "lon": 77.5893682}, {"type": "node", "id": 10697710450, "lat": 12.8480348, "lon": 77.5895674}, {"type": "node", "id": 10697710451, "lat": 12.8480581, "lon": 77.5894957}, {"type": "node", "id": 10697710452, "lat": 12.8479999, "lon": 77.5893882}, {"type": "node", "id": 10697710453, "lat": 12.8481863, "lon": 77.5891253}, {"type": "node", "id": 10801985095, "lat": 12.8708103, "lon": 77.5426386, "tags": {"addr:city": "Bangalore", "addr:postcode": "560062", "addr:street": "Kumarans School Holiday Village Road", "amenity": "school", "name": "Chethana Public School", "name:ta": "\u0b9a\u0bc7\u0ba4\u0bcd\u0ba4\u0ba9\u0bbe \u0baa\u0baa\u0bcd\u0bb3\u0bbf\u0b95\u0bcd \u0baa\u0bb3\u0bcd\u0bb3\u0bbf"}}, {"type": "node", "id": 10931529977, "lat": 12.8753065, "lon": 77.5613388}, {"type": "node", "id": 10931529983, "lat": 12.8762112, "lon": 77.5621647}, {"type": "node", "id": 10931529984, "lat": 12.8764622, "lon": 77.5616366}, {"type": "node", "id": 10931529985, "lat": 12.875466, "lon": 77.560966}, {"type": "node", "id": 10931530057, "lat": 12.876789, "lon": 77.5687122}, {"type": "node", "id": 10931530058, "lat": 12.8779552, "lon": 77.5692138}, {"type": "node", "id": 10931530118, "lat": 12.8836452, "lon": 77.5603805}, {"type": "node", "id": 10931530119, "lat": 12.8836735, "lon": 77.5601917}, {"type": "node", "id": 10947301792, "lat": 12.8233639, "lon": 77.5961968}, {"type": "node", "id": 10947301793, "lat": 12.8235966, "lon": 77.5972939}, {"type": "node", "id": 10947301794, "lat": 12.8247369, "lon": 77.597259}, {"type": "node", "id": 10947301795, "lat": 12.8245538, "lon": 77.5961378}, {"type": "node", "id": 10947301808, "lat": 12.8363486, "lon": 77.5999251}, {"type": "node", "id": 10947301809, "lat": 12.8360661, "lon": 77.6013064}, {"type": "node", "id": 10947301810, "lat": 12.8392069, "lon": 77.6021621}, {"type": "node", "id": 10947301811, "lat": 12.8396437, "lon": 77.6009229}, {"type": "node", "id": 11024816794, "lat": 12.8680793, "lon": 77.592286, "tags": {"access": "private", "barrier": "gate"}}, {"type": "node", "id": 11045697439, "lat": 12.8674784, "lon": 77.5413135}, {"type": "node", "id": 11124696368, "lat": 12.8545914, "lon": 77.5973918}, {"type": "node", "id": 11124696375, "lat": 12.854424, "lon": 77.5984807}, {"type": "node", "id": 11124696376, "lat": 12.8538775, "lon": 77.598407}, {"type": "node", "id": 11124696397, "lat": 12.8579516, "lon": 77.6053919}, {"type": "node", "id": 11124696398, "lat": 12.8597291, "lon": 77.6052194}, {"type": "node", "id": 11124696399, "lat": 12.8596873, "lon": 77.6046937}, {"type": "node", "id": 11124696405, "lat": 12.8579072, "lon": 77.6048501}, {"type": "node", "id": 11124696940, "lat": 12.8738788, "lon": 77.6126575}, {"type": "node", "id": 11124698206, "lat": 12.8733977, "lon": 77.598002}, {"type": "node", "id": 11124698325, "lat": 12.864617, "lon": 77.5869191}, {"type": "node", "id": 11124698326, "lat": 12.8657493, "lon": 77.5872248}, {"type": "node", "id": 11124698327, "lat": 12.8656813, "lon": 77.587477}, {"type": "node", "id": 11124698328, "lat": 12.8665573, "lon": 77.5876701}, {"type": "node", "id": 11124698345, "lat": 12.8723928, "lon": 77.591118}, {"type": "node", "id": 11124698398, "lat": 12.8727675, "lon": 77.5935025}, {"type": "node", "id": 11124781027, "lat": 12.8183137, "lon": 77.6016766}, {"type": "node", "id": 11124781028, "lat": 12.8176284, "lon": 77.6020521}, {"type": "node", "id": 11124781029, "lat": 12.8174401, "lon": 77.6029748}, {"type": "node", "id": 11124781030, "lat": 12.8173303, "lon": 77.6030606}, {"type": "node", "id": 11124781031, "lat": 12.8173041, "lon": 77.6036292}, {"type": "node", "id": 11124781032, "lat": 12.8173878, "lon": 77.6038706}, {"type": "node", "id": 11124781033, "lat": 12.8172727, "lon": 77.6043105}, {"type": "node", "id": 11124781034, "lat": 12.8175238, "lon": 77.6051688}, {"type": "node", "id": 11124781035, "lat": 12.818162, "lon": 77.6051795}, {"type": "node", "id": 11124781036, "lat": 12.8184235, "lon": 77.6050723}, {"type": "node", "id": 11124783958, "lat": 12.8498033, "lon": 77.5967896}, {"type": "node", "id": 11124783959, "lat": 12.8494424, "lon": 77.5974655}, {"type": "node", "id": 11124783960, "lat": 12.8509696, "lon": 77.5979}, {"type": "node", "id": 11124783961, "lat": 12.8513775, "lon": 77.5974897}, {"type": "node", "id": 11124783962, "lat": 12.8514821, "lon": 77.5973073}, {"type": "node", "id": 11178550165, "lat": 12.8187878, "lon": 77.6012103}, {"type": "node", "id": 11178768417, "lat": 12.8606762, "lon": 77.5427075, "tags": {"addr:street": "Vaibhava Sumukha Enclave Phase -1, Holiday Village Resort Road, Off Kanakapura Road, Mallasandra, Bengaluru", "amenity": "school", "name": "Cohesion Montessori"}}, {"type": "node", "id": 11549160980, "lat": 12.878567, "lon": 77.5854667}, {"type": "node", "id": 11549160981, "lat": 12.8786991, "lon": 77.5857134}, {"type": "node", "id": 11549160982, "lat": 12.8778181, "lon": 77.5861517}, {"type": "node", "id": 11618277667, "lat": 12.8662481, "lon": 77.5410318}, {"type": "node", "id": 11618278570, "lat": 12.8664344, "lon": 77.5410882}, {"type": "node", "id": 11722359071, "lat": 12.8728655, "lon": 77.6265648}, {"type": "node", "id": 11722359072, "lat": 12.8728119, "lon": 77.6258647}, {"type": "node", "id": 11722359073, "lat": 12.8735441, "lon": 77.6258352}, {"type": "node", "id": 11722359074, "lat": 12.8737467, "lon": 77.6257507}, {"type": "node", "id": 11763280918, "lat": 12.883501, "lon": 77.5608614}, {"type": "node", "id": 11870936052, "lat": 12.861708, "lon": 77.6173688}, {"type": "node", "id": 11870936053, "lat": 12.8615851, "lon": 77.6173715}, {"type": "node", "id": 11870936054, "lat": 12.8613353, "lon": 77.6183492}, {"type": "node", "id": 11870936055, "lat": 12.8613118, "lon": 77.6187327}, {"type": "node", "id": 11870936056, "lat": 12.8608097, "lon": 77.6187327}, {"type": "node", "id": 11870936057, "lat": 12.8602057, "lon": 77.6186255}, {"type": "node", "id": 11870936058, "lat": 12.8603495, "lon": 77.6181775}, {"type": "node", "id": 11870936059, "lat": 12.8602737, "lon": 77.6178557}, {"type": "node", "id": 11870936060, "lat": 12.8602685, "lon": 77.6172388}, {"type": "node", "id": 11870936061, "lat": 12.8603861, "lon": 77.6169705}, {"type": "node", "id": 11870936062, "lat": 12.8610189, "lon": 77.6171744}, {"type": "node", "id": 11870936063, "lat": 12.8617629, "lon": 77.6171958}, {"type": "node", "id": 11870936170, "lat": 12.86091, "lon": 77.6101711}, {"type": "node", "id": 11870936171, "lat": 12.8619172, "lon": 77.6102449}, {"type": "node", "id": 11870936172, "lat": 12.8618466, "lon": 77.6110549}, {"type": "node", "id": 11870936173, "lat": 12.8610179, "lon": 77.6109844}, {"type": "node", "id": 11871336253, "lat": 12.8731816, "lon": 77.6116732}, {"type": "node", "id": 12022725570, "lat": 12.8842841, "lon": 77.550838}, {"type": "node", "id": 12150945799, "lat": 12.8458171, "lon": 77.6079829}, {"type": "node", "id": 12294200271, "lat": 12.8640633, "lon": 77.5787826}, {"type": "node", "id": 12294200272, "lat": 12.863611, "lon": 77.5787665}, {"type": "node", "id": 12294214710, "lat": 12.8599547, "lon": 77.5687779}, {"type": "node", "id": 12294214711, "lat": 12.8602698, "lon": 77.5690126}, {"type": "node", "id": 12294214712, "lat": 12.860917, "lon": 77.5680363}, {"type": "node", "id": 12294214713, "lat": 12.8604567, "lon": 77.5677413}, {"type": "node", "id": 12369330470, "lat": 12.8532538, "lon": 77.5699501}, {"type": "node", "id": 12369330471, "lat": 12.8531034, "lon": 77.5706072}, {"type": "node", "id": 12369330472, "lat": 12.8531414, "lon": 77.5706327}, {"type": "node", "id": 12369330473, "lat": 12.8539677, "lon": 77.5705723}, {"type": "node", "id": 12369330474, "lat": 12.8540697, "lon": 77.5701432}, {"type": "node", "id": 12369602763, "lat": 12.853224, "lon": 77.5700802}, {"type": "node", "id": 12448043187, "lat": 12.8667003, "lon": 77.5411558}, {"type": "node", "id": 12448043188, "lat": 12.8667665, "lon": 77.5409192}, {"type": "node", "id": 12448043189, "lat": 12.8672868, "lon": 77.5410131}, {"type": "node", "id": 12448043190, "lat": 12.8672574, "lon": 77.5412746}, {"type": "node", "id": 12448043191, "lat": 12.8675821, "lon": 77.5413307}, {"type": "node", "id": 12448043192, "lat": 12.8676869, "lon": 77.5402862}, {"type": "node", "id": 12448043193, "lat": 12.867564, "lon": 77.5400931}, {"type": "node", "id": 12448043194, "lat": 12.8676243, "lon": 77.5393247}, {"type": "node", "id": 12448043196, "lat": 12.86696, "lon": 77.5399482}, {"type": "node", "id": 12448043197, "lat": 12.8658422, "lon": 77.5397611}, {"type": "node", "id": 12488315347, "lat": 12.8842337, "lon": 77.550896}, {"type": "node", "id": 12488315348, "lat": 12.8845452, "lon": 77.5518779}, {"type": "node", "id": 12488315349, "lat": 12.8849169, "lon": 77.5517853}, {"type": "node", "id": 12488315350, "lat": 12.8850124, "lon": 77.5509629}, {"type": "node", "id": 12488315454, "lat": 12.8805574, "lon": 77.5468567}, {"type": "node", "id": 12488315464, "lat": 12.8809121, "lon": 77.5468866}, {"type": "node", "id": 12488315465, "lat": 12.881047, "lon": 77.5463806}, {"type": "node", "id": 12528722274, "lat": 12.8665248, "lon": 77.5905699}, {"type": "node", "id": 12555503809, "lat": 12.846881, "lon": 77.5952245}, {"type": "node", "id": 12555503810, "lat": 12.8472235, "lon": 77.5953667}, {"type": "node", "id": 12555503811, "lat": 12.8474406, "lon": 77.5948946}, {"type": "node", "id": 12555503812, "lat": 12.8470248, "lon": 77.5947498}, {"type": "node", "id": 12555503872, "lat": 12.8538043, "lon": 77.5971705}, {"type": "node", "id": 12555764486, "lat": 12.8497026, "lon": 77.6000042}, {"type": "node", "id": 12555764487, "lat": 12.8495339, "lon": 77.6006345}, {"type": "node", "id": 12555764488, "lat": 12.8499, "lon": 77.6006681}, {"type": "node", "id": 12555764489, "lat": 12.8500347, "lon": 77.6000069}, {"type": "node", "id": 12555764490, "lat": 12.8482016, "lon": 77.5986779}, {"type": "node", "id": 12555764491, "lat": 12.8480329, "lon": 77.599846}, {"type": "node", "id": 12555764492, "lat": 12.8486069, "lon": 77.5999036}, {"type": "node", "id": 12555764493, "lat": 12.8485964, "lon": 77.5993551}, {"type": "node", "id": 12555764494, "lat": 12.848671, "lon": 77.5988093}, {"type": "node", "id": 12555786508, "lat": 12.8680134, "lon": 77.5922619}, {"type": "node", "id": 12555786532, "lat": 12.8681361, "lon": 77.5923069}, {"type": "node", "id": 12555786533, "lat": 12.8621852, "lon": 77.5850549}, {"type": "node", "id": 12555786534, "lat": 12.8622702, "lon": 77.5851341}, {"type": "node", "id": 12555786535, "lat": 12.8625487, "lon": 77.5852025}, {"type": "node", "id": 12555786536, "lat": 12.8625042, "lon": 77.5856316}, {"type": "node", "id": 12555786537, "lat": 12.8622506, "lon": 77.5865865}, {"type": "node", "id": 12555786538, "lat": 12.8619838, "lon": 77.5869137}, {"type": "node", "id": 12555786539, "lat": 12.862831, "lon": 77.5873723}, {"type": "node", "id": 12555786540, "lat": 12.8638313, "lon": 77.5876339}, {"type": "node", "id": 12555786541, "lat": 12.8641333, "lon": 77.5868145}, {"type": "node", "id": 12555786542, "lat": 12.8670442, "lon": 77.5861123}, {"type": "node", "id": 12555786543, "lat": 12.8640104, "lon": 77.5843146}, {"type": "node", "id": 12555786544, "lat": 12.8645752, "lon": 77.5850496}, {"type": "node", "id": 12555786545, "lat": 12.8647439, "lon": 77.585586}, {"type": "node", "id": 12555786546, "lat": 12.8643451, "lon": 77.5855096}, {"type": "node", "id": 12555786547, "lat": 12.8639162, "lon": 77.5852896}, {"type": "node", "id": 12555786548, "lat": 12.863758, "lon": 77.5852413}, {"type": "node", "id": 12555786549, "lat": 12.863388, "lon": 77.5851327}, {"type": "node", "id": 12555786550, "lat": 12.8626153, "lon": 77.5851166}, {"type": "node", "id": 12555786551, "lat": 12.8623643, "lon": 77.5850563}, {"type": "node", "id": 12555786552, "lat": 12.8623185, "lon": 77.5849892}, {"type": "node", "id": 12555786560, "lat": 12.8661101, "lon": 77.589156}, {"type": "node", "id": 12555786636, "lat": 12.8616664, "lon": 77.5911179}, {"type": "node", "id": 12555786637, "lat": 12.861572, "lon": 77.5916491}, {"type": "node", "id": 12555786638, "lat": 12.8620152, "lon": 77.5917296}, {"type": "node", "id": 12555786707, "lat": 12.8596135, "lon": 77.6052306}, {"type": "node", "id": 12555786872, "lat": 12.8661337, "lon": 77.5964624}, {"type": "node", "id": 12555786873, "lat": 12.8659833, "lon": 77.5963202}, {"type": "node", "id": 12555786874, "lat": 12.8658578, "lon": 77.5972992}, {"type": "node", "id": 12555786875, "lat": 12.865948, "lon": 77.597322}, {"type": "node", "id": 12555786876, "lat": 12.8659297, "lon": 77.5974937}, {"type": "node", "id": 12555786877, "lat": 12.8660696, "lon": 77.5975151}, {"type": "node", "id": 12555786878, "lat": 12.8660173, "lon": 77.5980221}, {"type": "node", "id": 12555786879, "lat": 12.8661127, "lon": 77.5979832}, {"type": "node", "id": 12555786880, "lat": 12.8661768, "lon": 77.5970793}, {"type": "node", "id": 12555786881, "lat": 12.8662526, "lon": 77.5965093}, {"type": "node", "id": 12555787002, "lat": 12.8665298, "lon": 77.5904918}, {"type": "node", "id": 12555787003, "lat": 12.866805, "lon": 77.5904714}, {"type": "node", "id": 12555816420, "lat": 12.8636646, "lon": 77.57718}, {"type": "node", "id": 12555816421, "lat": 12.8641169, "lon": 77.577196}, {"type": "node", "id": 12941891201, "lat": 12.8803607, "lon": 77.5796688, "tags": {"addr:postcode": "560076", "amenity": "school", "name": "Orchids The International School"}}, {"type": "node", "id": 13014788881, "lat": 12.8400333, "lon": 77.5998111}, {"type": "node", "id": 13014788882, "lat": 12.8384904, "lon": 77.5994866}, {"type": "node", "id": 13014788883, "lat": 12.838323, "lon": 77.6000552}, {"type": "node", "id": 13014788884, "lat": 12.837749, "lon": 77.5998875}, {"type": "node", "id": 13014788885, "lat": 12.8375385, "lon": 77.5998393}, {"type": "node", "id": 13014788886, "lat": 12.8371553, "lon": 77.5997628}, {"type": "node", "id": 13014788887, "lat": 12.8365231, "lon": 77.5996642}, {"type": "node", "id": 13075437208, "lat": 12.8674402, "lon": 77.5393624}, {"type": "node", "id": 13075437209, "lat": 12.8674219, "lon": 77.5396227}, {"type": "node", "id": 13075439575, "lat": 12.8658695, "lon": 77.5330984}, {"type": "node", "id": 13075439576, "lat": 12.8648785, "lon": 77.5342499}, {"type": "node", "id": 13075439577, "lat": 12.8651871, "lon": 77.5343169}, {"type": "node", "id": 13075439578, "lat": 12.8651949, "lon": 77.5337134}, {"type": "node", "id": 13075439579, "lat": 12.8648838, "lon": 77.5334935}, {"type": "node", "id": 13156098429, "lat": 12.8125071, "lon": 77.5865446}, {"type": "node", "id": 13156098454, "lat": 12.8124709, "lon": 77.5867259}, {"type": "node", "id": 13156098455, "lat": 12.8128632, "lon": 77.5868922}, {"type": "node", "id": 13156098456, "lat": 12.8129207, "lon": 77.5870264}, {"type": "node", "id": 13156098457, "lat": 12.8149764, "lon": 77.5876754}, {"type": "node", "id": 13156098458, "lat": 12.8151072, "lon": 77.5871176}, {"type": "node", "id": 13156098459, "lat": 12.8146417, "lon": 77.5870156}, {"type": "node", "id": 13156098460, "lat": 12.8149189, "lon": 77.5857443}, {"type": "node", "id": 13156098461, "lat": 12.8143854, "lon": 77.5855941}, {"type": "node", "id": 13156098462, "lat": 12.8140003, "lon": 77.5856053}, {"type": "node", "id": 13156098463, "lat": 12.8139093, "lon": 77.5859964}, {"type": "node", "id": 13156098464, "lat": 12.8131195, "lon": 77.5858033}, {"type": "node", "id": 13156098465, "lat": 12.8130829, "lon": 77.5858998}, {"type": "node", "id": 13156098466, "lat": 12.8126539, "lon": 77.5858086}, {"type": "node", "id": 13156098487, "lat": 12.8193777, "lon": 77.5849687}, {"type": "node", "id": 13156098488, "lat": 12.8186824, "lon": 77.5846392}, {"type": "node", "id": 13156098489, "lat": 12.8185203, "lon": 77.5855377}, {"type": "node", "id": 13156098490, "lat": 12.8185412, "lon": 77.5861037}, {"type": "node", "id": 13156098491, "lat": 12.8189845, "lon": 77.5862382}, {"type": "node", "id": 13156098528, "lat": 12.8242757, "lon": 77.5814785}, {"type": "node", "id": 13156098529, "lat": 12.8241066, "lon": 77.5823539}, {"type": "node", "id": 13156098531, "lat": 12.8275501, "lon": 77.5862591}, {"type": "node", "id": 13156098560, "lat": 12.8390984, "lon": 77.5941557}, {"type": "node", "id": 13156098561, "lat": 12.8393456, "lon": 77.5935186}, {"type": "node", "id": 13165794469, "lat": 12.8361027, "lon": 77.6002926}, {"type": "node", "id": 13165794470, "lat": 12.8358961, "lon": 77.6002738}, {"type": "node", "id": 13165794471, "lat": 12.8358857, "lon": 77.6004454}, {"type": "node", "id": 13165794472, "lat": 12.8362597, "lon": 77.6004776}, {"type": "node", "id": 13165794473, "lat": 12.8459618, "lon": 77.6080388}, {"type": "node", "id": 13165794474, "lat": 12.8457996, "lon": 77.6090044}, {"type": "node", "id": 13165794475, "lat": 12.8457107, "lon": 77.6089722}, {"type": "node", "id": 13165794476, "lat": 12.8456689, "lon": 77.6091814}, {"type": "node", "id": 13165794477, "lat": 12.8460533, "lon": 77.609227}, {"type": "node", "id": 13165794478, "lat": 12.8463854, "lon": 77.6086879}, {"type": "node", "id": 13165794479, "lat": 12.8468195, "lon": 77.6071751}, {"type": "node", "id": 13165794480, "lat": 12.8460441, "lon": 77.6067929}, {"type": "node", "id": 13269838280, "lat": 12.7951036, "lon": 77.617399}, {"type": "node", "id": 13269838281, "lat": 12.7949365, "lon": 77.6178051}, {"type": "node", "id": 13269838282, "lat": 12.7953866, "lon": 77.6179999}, {"type": "node", "id": 13269838283, "lat": 12.7955537, "lon": 77.6175938}, {"type": "node", "id": 13270605466, "lat": 12.8150639, "lon": 77.5873024}, {"type": "way", "id": 120108572, "nodes": [1347489613, 1347489615, 1347489620, 1347489616, 1347489613], "tags": {"amenity": "school", "name": "Gurukul School", "name:kn": "\u0c97\u0cc1\u0cb0\u0cc1\u0c95\u0cc1\u0cb2"}}, {"type": "way", "id": 133243116, "nodes": [1466630508, 1466630506, 1466630512, 1466630510, 1466630507, 1466630508], "tags": {"amenity": "school", "name": "Silicon City Public School"}}, {"type": "way", "id": 137318791, "nodes": [1506342162, 1720796236, 1720796337, 1720796075, 1720796300, 1720796200, 1506342124, 1506342103, 1506342171, 1506342144, 1506342150, 1506342162], "tags": {"amenity": "school", "name": "Ryan International School"}}, {"type": "way", "id": 137320977, "nodes": [1506370724, 1506370774, 1506370642, 1506370744, 1506370729, 1506370745, 1506370687, 1506370722, 1506370681, 1506370662, 1506370691, 1506370670, 1506370719, 1506370689, 1506370666, 1506370740, 1506370668, 1506370781, 1506370778, 1506370707, 1506370696, 1506370658, 1506370655, 1506370720, 1506370660, 1506370725, 1506370645, 1506370723, 1506370651, 1506370704, 1506370747, 1506370653, 1506370717, 1506370643, 1506370710, 1506370688, 1506370738, 10570186219, 1506370644, 1506370724], "tags": {"amenity": "school", "name": "Sarala Birla Academy", "name:kn": "\u0cb8\u0cb0\u0cb2\u0cbe \u0cac\u0cbf\u0cb0\u0cb2\u0cbe \u0c85\u0c95\u0ca1\u0cc6\u0cae\u0cbf"}}, {"type": "way", "id": 180799883, "nodes": [1912643793, 1912643794, 11178550165, 1912643789, 1912643792, 1912643790, 1912643793], "tags": {"amenity": "school", "name": "The Samhitha Acdemy"}}, {"type": "way", "id": 180799884, "nodes": [1912643795, 1912643790, 1912643792, 1912643789, 1912643788, 1912643791, 1912643795], "tags": {"amenity": "school", "name": "PSBB Learning Leaderhip Academy"}}, {"type": "way", "id": 188431720, "nodes": [1990609317, 1990609277, 1990609264, 13075439575, 1990609263, 1990609262, 1990609280, 1990609317], "tags": {"amenity": "school", "name": "Jnana Sweekar Public School"}}, {"type": "way", "id": 191101727, "nodes": [2016849181, 2016849180, 2016849178, 2016849177, 2016849179, 2016849182, 2016849181], "tags": {"amenity": "school", "building": "yes", "name": "Lady Wellington High School"}}, {"type": "way", "id": 198161707, "nodes": [2083338356, 2083338352, 2083338354, 2083338358, 2083338356], "tags": {"amenity": "school", "building": "yes", "name": "Sri Maruthi Primary & High School", "name:kn": "\u0cb6\u0ccd\u0cb0\u0cc0 \u0cae\u0cbe\u0cb0\u0cc1\u0ca4\u0cbf \u0cb6\u0cbe\u0cb2\u0cc6"}}, {"type": "way", "id": 216574077, "nodes": [2259659279, 2259659282, 2259659281, 2259659285, 2259659284, 2259659283, 2259659279], "tags": {"amenity": "school", "name": "Janak Vidhyalaya", "name:kn": "\u0c9c\u0ca8\u0c95 \u0cb5\u0cbf\u0ca6\u0ccd\u0caf\u0cbe\u0cb2\u0caf"}}, {"type": "way", "id": 236678607, "nodes": [3417162334, 6406272357, 3417162327, 3417162326, 2446754419, 3417162334], "tags": {"addr:place": "Arakere", "amenity": "school", "isced:level": "3", "name": "AECS Magnolia Maruthi Public School, Arakere", "name:kn": "\u0c8e.\u0c87.\u0cb8\u0cbf.\u0c8e\u0cb8\u0ccd \u0cae\u0ccd\u0caf\u0cbe\u0c97\u0ccd\u0ca8\u0ccb\u0cb2\u0cbf\u0caf\u0cbe \u0cae\u0cbe\u0cb0\u0cc1\u0ca4\u0cbf \u0caa\u0cac\u0ccd\u0cb2\u0cbf\u0c95\u0ccd \u0cb6\u0cbe\u0cb2\u0cc6, \u0c85\u0cb0\u0c95\u0cc6\u0cb0\u0cc6", "operator": "Private", "school": "Higher Secondary"}}, {"type": "way", "id": 290364531, "nodes": [2939021471, 2939021456, 4076243872, 4076243870, 2939021470, 4076243862, 4076243860, 4076243858, 4076243859, 4076243861, 2939021475, 2939021444, 4076243863, 4076243864, 4076243865, 2939021450, 4076243866, 4076243867, 2939021455, 4076243868, 4076243869, 4076243871, 4076243873, 4076243874, 4076243875, 2939021471], "tags": {"alt_name": "BGS NPS", "amenity": "school", "name": "BGS National Public School"}}, {"type": "way", "id": 307414834, "nodes": [3125515003, 3125514998, 3125514999, 3125515000, 3125515001, 3125515005, 3125515006, 3125515002, 3125515004, 3125515007, 3125515003], "tags": {"amenity": "school", "building": "yes", "name": "Ekya", "name:kn": "\u0c8f\u0c95\u0ccd\u0caf\u0cbe \u0cb6\u0cbe\u0cb2\u0cc6", "source": "GPS"}}, {"type": "way", "id": 308189767, "nodes": [3134803465, 3134803466, 3134803467, 3134803468, 3134803465], "tags": {"amenity": "school", "name": "Christ Academy ICSE School"}}, {"type": "way", "id": 334653046, "nodes": [3417146661, 3417146660, 3417146657, 3417146659, 3417146661], "tags": {"amenity": "school", "name": "Government High School", "name:kn": "\u0cb8\u0cb0\u0ccd\u0c95\u0cbe\u0cb0\u0cbf \u0caa\u0ccd\u0cb0\u0ccc\u0ca2 \u0cb6\u0cbe\u0cb2\u0cc6"}}, {"type": "way", "id": 347137534, "nodes": [3535384415, 3535384416, 3535384414, 3535384413, 3535384415], "tags": {"amenity": "school", "building": "yes", "name": "Loyola Primary School", "name:kn": "\u0cb2\u0ccb\u0caf\u0cb2 \u0caa\u0ccd\u0cb0\u0cbe\u0ca5\u0cae\u0cbf\u0c95 \u0caa\u0cbe\u0ca0 \u0cb6\u0cbe\u0cb2\u0cc6"}}, {"type": "way", "id": 347147615, "nodes": [3535459604, 3535459188, 3535459159, 3535459168, 3535459129, 3535459133, 3535459176, 3535459604], "tags": {"addr:city": "Begur", "alt_name": "GMPS Begur", "amenity": "school", "building": "yes", "name": "Government Lower Primary School", "name:kn": "\u0cb8\u0cb0\u0ccd\u0c95\u0cbe\u0cb0\u0cbf \u0cb9\u0cbf\u0cb0\u0cbf\u0caf \u0caa\u0ccd\u0cb0\u0cbe\u0ca5\u0cae\u0cbf\u0c95 \u0cb6\u0cbe\u0cb2\u0cc6 \u0cac\u0cc7\u0c97\u0cc2\u0cb0\u0cc1"}}, {"type": "way", "id": 557689233, "nodes": [5378252760, 5378252761, 5378252762, 5378252763, 5378252760], "tags": {"amenity": "school"}}, {"type": "way", "id": 668612959, "nodes": [6261304462, 11124698206, 6261304468, 6261304469, 10579312528, 6261304472, 6261304473, 6261304474, 4483748622, 6261304459, 6261304462], "tags": {"amenity": "school", "name": "SOS Children's Village"}}, {"type": "way", "id": 678333101, "nodes": [6351593514, 6351593515, 6351593516, 3543380603, 6351593517, 6351593514], "tags": {"amenity": "school", "name": "Aradhana Academy"}}, {"type": "way", "id": 710637794, "nodes": [6681252707, 6681252708, 6681252709, 6681297603, 6681285587, 6681252710, 6681252707], "tags": {"amenity": "school", "email": "info@mutha.edu.in", "name": "The Mutha School", "operator": "Mutha Foundation", "operator:type": "private", "phone": "+91 99450 27007", "school:gender": "mixed", "website": "https://mutha.edu.in"}}, {"type": "way", "id": 775660976, "nodes": [7236242036, 7236242035, 7236242084, 10931530119, 10931530118, 11763280918, 7236242083, 7236242034, 7236242033, 7236242032, 7236242031, 7236242036], "tags": {"addr:city": "Bengaluru", "addr:country": "IN", "addr:housenumber": "28/4", "addr:postcode": "560062", "addr:street": "Kanakapura Road", "addr:suburb": "Doddakalasandra", "amenity": "school", "email": "cbsedks@kumarans.org", "name": "Sri Kumaran Children's Academy", "phone": "+91 80 2632 1077", "school:gender": "mixed", "website": "https://cbse-dks.kumarans.org/"}}, {"type": "way", "id": 781680947, "nodes": [7298163634, 7298163657, 7298163656, 7298163655, 7298163654, 7298163653, 7298163652, 7298163585, 7298163651, 7298163635, 7298163634], "tags": {"addr:postcode": "560062", "amenity": "school", "name": "Sri Kumaran Children's Home CBSE", "name:en": "Sri Kumaran Children's Home CBSE", "phone": "65839365", "website": "http://pupilpod.kumarans.org"}}, {"type": "way", "id": 781680950, "nodes": [7298163635, 7298163665, 7298163664, 7298163663, 7298163662, 7298163661, 7298163660, 7298163659, 7298163658, 7298163634, 7298163635], "tags": {"addr:postcode": "560064", "amenity": "school", "name": "Sri Kumaran Children's Home ICSE", "name:en": "Sri Kumaran Children's Home ICSE", "website": "http://pupilpod.kumarans.org"}}, {"type": "way", "id": 901563734, "nodes": [7331742678, 7331742669, 7331742676, 7331742673, 7331742688, 7331742696, 7331742697, 7331742701, 7331742710, 7331742667, 7331742668, 8375016087, 10185153752, 7331742678], "tags": {"addr:city": "Bangluru", "addr:postcode": "560105", "addr:street": "Koppa-harapanhalli Road", "amenity": "school", "email": "admissions@candorschool.com", "grades": "0-12", "name": "Candor International School", "phone": "+91 77602 99995", "religion": "none", "school:gender": "mixed", "website": "https://candorschool.edu.in/"}}, {"type": "way", "id": 1082360480, "nodes": [9919570162, 9919570161, 9919570160, 9919570159, 9919570158, 9919570153, 11124698398, 9919570162], "tags": {"amenity": "school", "name": "Holy Spirit School ICSE"}}, {"type": "way", "id": 1082360481, "nodes": [9919570165, 11124698345, 9919570164, 9919570156, 7682106724, 7682106731, 9919570163, 7682106734, 9919570165], "tags": {"amenity": "school", "name": "Holy Spirit PU College"}}, {"type": "way", "id": 1082360490, "nodes": [9919570238, 9919570237, 9919570236, 9919570235, 12555786532, 11024816794, 12555786508, 9919570241, 9919570240, 12528722274, 12555787002, 12555787003, 9919570225, 9919570224, 9919570226, 9919570223, 9919570222, 9919570228, 9919570227, 9919570246, 9919570234, 9919570245, 9919570244, 9919570243, 9919570242, 9919570238], "tags": {"amenity": "school", "name": "Mount St. Joseph", "name:kn": "\u0cae\u0ccc\u0c82\u0c9f\u0ccd \u0cb8\u0cc6\u0c82\u0c9f\u0ccd \u0c9c\u0ccd\u0caf\u0ccb\u0cb8\u0cc6\u0cab\u0ccd"}}, {"type": "way", "id": 1088218591, "nodes": [9970411106, 13156098531, 9970411105, 9970411104, 9970411103, 9970411106], "tags": {"amenity": "school"}}, {"type": "way", "id": 1149959393, "nodes": [10697710348, 10697710349, 10697710350, 10697710351, 10697710352, 10697710353, 10697710348], "tags": {"amenity": "school", "name": "Carmel Academy"}}, {"type": "way", "id": 1149959414, "nodes": [2056455541, 10697710446, 10697710447, 10697710448, 10697710449, 10697710450, 10697710451, 10697710452, 10697710453, 2056455541], "tags": {"amenity": "school", "name": "Sherwood High School"}}, {"type": "way", "id": 1176579513, "nodes": [10931529985, 10931529977, 10233431244, 10931529983, 10931529984, 10931529985], "tags": {"amenity": "school", "name": "Doddakalasandra Government High School"}}, {"type": "way", "id": 1176579524, "nodes": [7236242192, 10931530058, 10931530057, 7236242191, 7236242192], "tags": {"amenity": "school", "name": "DPS Bengaluru South, Junior School"}}, {"type": "way", "id": 1178402465, "nodes": [10947301795, 10947301794, 10947301793, 10947301792, 10947301795], "tags": {"amenity": "school", "name": "Sudarshan Vidhya Mandira CBSE Campus"}}, {"type": "way", "id": 1178402467, "nodes": [13014788887, 13014788886, 13014788885, 13014788884, 13014788883, 13014788882, 13014788881, 10947301811, 10947301810, 10947301809, 13165794472, 13165794471, 13165794470, 13165794469, 10947301808, 13014788887], "tags": {"amenity": "school", "name": "Greenwood High Bannerghatta"}}, {"type": "way", "id": 1199400828, "nodes": [11124696399, 11124696398, 12555786707, 11124696397, 11124696405, 11124696399], "tags": {"amenity": "school", "name": "VIBGYOR High School"}}, {"type": "way", "id": 1199400874, "nodes": [11124696940, 6430489237, 9892036293, 11871336253, 9892036294, 9892036295, 11124696940], "tags": {"addr:place": "Begur", "amenity": "school", "isced:level": "3", "name": "St Anns School, Begur", "name:kn": "\u0cb8\u0cc6\u0c82\u0c9f\u0ccd \u0c86\u0ca8\u0ccd\u0cb8\u0ccd \u0cb6\u0cbe\u0cb2\u0cc6, \u0cac\u0cc7\u0c97\u0cc2\u0cb0\u0cc1", "operator": "Private Un-Aided", "school": "Higher Secondary"}}, {"type": "way", "id": 1199410717, "nodes": [11124781027, 11124781036, 11124781035, 11124781034, 11124781033, 11124781032, 11124781031, 11124781030, 11124781029, 11124781028, 11124781027], "tags": {"amenity": "school"}}, {"type": "way", "id": 1199410767, "nodes": [11124783962, 11124783961, 11124783960, 11124783959, 11124783958, 11124783962], "tags": {"amenity": "school", "name": "St. Joseph Nivas Special School"}}, {"type": "way", "id": 1242749610, "nodes": [11549160982, 11549160981, 11549160980, 8809336714, 9919570146, 11549160982], "tags": {"amenity": "school", "name": "Skalvi International School", "opening_hours": "Mo-Sa 08:00-16:00"}}, {"type": "way", "id": 1261422248, "nodes": [10242924636, 11722359074, 11722359073, 11722359072, 11722359071, 10242924638, 10242924637, 10242924636], "tags": {"amenity": "school", "name": "St. Teresa School, Begur", "name:kn": "\u0cb8\u0c82\u0ca4 \u0ca4\u0cc6\u0cb0\u0cc7\u0cb8\u0cb0 \u0cb6\u0cbe\u0cb2\u0cc6"}}, {"type": "way", "id": 1278704434, "nodes": [11870936063, 11870936062, 11870936061, 11870936060, 11870936059, 11870936058, 11870936057, 11870936056, 11870936055, 11870936054, 11870936053, 11870936052, 11870936063], "tags": {"amenity": "school", "landuse": "education", "name": "St. Anthony's School"}}, {"type": "way", "id": 1278704457, "nodes": [11870936173, 11870936172, 11870936171, 11870936170, 10220948541, 11870936173], "tags": {"amenity": "school", "landuse": "education", "name": "Chrysalis High School, Begur"}}, {"type": "way", "id": 1328835818, "nodes": [12294214713, 12294214712, 12294214711, 12294214710, 12294214713], "tags": {"amenity": "school"}}, {"type": "way", "id": 1337330212, "nodes": [12369330474, 12369330473, 12369330472, 12369330471, 12369602763, 12369330470, 12369330474], "tags": {"amenity": "school"}}, {"type": "way", "id": 1345637273, "nodes": [12448043197, 12448043196, 1990604303, 13075437209, 13075437208, 12448043194, 12448043193, 12448043192, 12448043191, 11045697439, 12448043190, 12448043189, 12448043188, 12448043187, 11618278570, 11618277667, 1990604297, 1990604302, 12448043197], "tags": {"amenity": "school", "landuse": "education", "name": "Deeksha"}}, {"type": "way", "id": 1349974772, "nodes": [12488315350, 12488315349, 12488315348, 12488315347, 12022725570, 12488315350], "tags": {"amenity": "school"}}, {"type": "way", "id": 1349974796, "nodes": [1990609977, 12488315454, 1990609982, 1990609978, 1990609972, 12488315465, 12488315464, 1990609977], "tags": {"amenity": "school", "name": "Siddaganga National School", "name:kn": "\u0cb8\u0cbf\u0ca6\u0ccd\u0ca6\u0c97\u0c82\u0c97 \u0cb6\u0cbe\u0cb2\u0cc6"}}, {"type": "way", "id": 1356594011, "nodes": [12555503812, 12555503811, 12555503810, 12555503809, 12555503812], "tags": {"amenity": "school"}}, {"type": "way", "id": 1356594026, "nodes": [11124696376, 12555503872, 11124696368, 11124696375, 11124696376], "tags": {"amenity": "school"}}, {"type": "way", "id": 1356594054, "nodes": [12555764489, 12555764488, 12555764487, 6349202651, 12555764486, 12555764489], "tags": {"addr:place": "Chikkana Halli", "amenity": "school", "isced:level": "2", "name": "Saint Francis Xavier HPS Chikkana Halli", "name:kn": "\u0cb8\u0cc6\u0c82\u0c9f\u0ccd\u200c \u0cab\u0ccd\u0cb0 \u0c95\u0ccd\u0cb8\u0cc7\u0cb5\u0cbf\u0caf\u0cb0\u0ccd \u0cb9\u0cbf\u0cb0\u0cbf\u0caf \u0caa\u0ccd\u0cb0\u0cbe\u0ca5\u0cae\u0cbf\u0c95 \u0cb6\u0cbe\u0cb2\u0cc6 \u0c9a\u0cbf\u0c95\u0ccd\u0c95\u0c95\u0cae\u0ccd\u0cae\u0ca8 \u0cb9\u0cb3\u0ccd\u0cb3\u0cbf", "operator": "Pvt. Aided", "school": "primary"}}, {"type": "way", "id": 1356594056, "nodes": [12555764494, 12555764493, 12555764492, 12555764491, 12555764490, 12555764494], "tags": {"amenity": "school"}}, {"type": "way", "id": 1356597042, "nodes": [12555786552, 12555786551, 12555786550, 12555786549, 12555786548, 12555786547, 12555786546, 12555786545, 12555786544, 12555786543, 9919570195, 9919570200, 9919570199, 12555786542, 9919570229, 9919570227, 9919570228, 9919570222, 12555786560, 1210191575, 1210191567, 1210191570, 1210191549, 11124698328, 11124698327, 11124698326, 11124698325, 12555786541, 12555786540, 12555786539, 12555786538, 12555786537, 12555786536, 12555786535, 12555786534, 12555786533, 12555786552], "tags": {"amenity": "school", "name": "Sri Ramakrishna Samagra Shikshana Kendra"}}, {"type": "way", "id": 1356597055, "nodes": [10697710358, 12555786638, 12555786637, 12555786636, 10697710358], "tags": {"amenity": "school"}}, {"type": "way", "id": 1356597110, "nodes": [12555786881, 12555786880, 12555786879, 12555786878, 12555786877, 12555786876, 12555786875, 12555786874, 12555786873, 12555786872, 12555786881], "tags": {"amenity": "school"}}, {"type": "way", "id": 1356599513, "nodes": [12555816421, 12294200271, 12294200272, 12555816420, 12555816421], "tags": {"amenity": "school", "name": "Sri Chaitanya Techno School"}}, {"type": "way", "id": 1422781175, "nodes": [13075439579, 13075439578, 13075439577, 13075439576, 13075439579], "tags": {"amenity": "school"}}, {"type": "way", "id": 1431247727, "nodes": [13156098466, 13156098465, 13156098464, 13156098463, 13156098462, 13156098461, 13156098460, 13156098459, 13156098458, 13270605466, 13156098457, 13156098456, 13156098455, 13156098454, 13156098429, 13156098466], "tags": {"amenity": "school"}}, {"type": "way", "id": 1431247729, "nodes": [13156098491, 13156098490, 13156098489, 13156098488, 13156098487, 13156098491], "tags": {"amenity": "school"}}, {"type": "way", "id": 1431247733, "nodes": [4142629715, 13156098529, 13156098528, 4142629714, 4142629715], "tags": {"amenity": "school"}}, {"type": "way", "id": 1432358339, "nodes": [1837284567, 7928087585, 13156098560, 13156098561, 1837284567], "tags": {"addr:housenumber": "93/2", "addr:postcode": "560083", "addr:street": "Hommadevanahalli Village Begur Hobli, Bengaluru South, Taluk", "amenity": "school", "email": "communications.oisbg@orchids.edu.in", "name": "Orchids The International School - Yelahanka", "name:en": "Orchids The International School, Bannerghatta", "opening_hours": "Mo-Su 09:00-18:30", "operator": "Orchids International School", "phone": "9513731352", "website": "https://www.orchidsinternationalschool.com/bangalore-branches/bannerghatta/"}}, {"type": "way", "id": 1432358344, "nodes": [13165794480, 13165794479, 13165794478, 13165794477, 13165794476, 13165794475, 13165794474, 13165794473, 12150945799, 13165794480], "tags": {"amenity": "school"}}, {"type": "way", "id": 1446231711, "nodes": [13269838280, 13269838283, 13269838282, 13269838281, 13269838280], "tags": {"amenity": "school", "name": "Tapovan School"}}]}